Workbook

Sheet Projectbegroting
A1: * Als vorig projectnummer wordt ingevuld worden automatisch de gegevens gevuld vanuit vorig jaar. Wil je hier vanaf wijken, kijk dan in de dopdownlijst in kolom C, voor de keuze en Vul deze in bij Kolom B. | J1: jaar | K1: 46023
A2: Invulvelden | J2: Index | K2: 0
A5: Bedrijf | B5: BV | C5: Voorbeeldlijsten
A6: Vorig projectnummer | B6: 30626-0002
A7: Projectnaam vorig | B7: =_xlfn.XLOOKUP(B6,'report B_Project'!B:B,'report B_Project'!C:C,"niet bekend") -> Klant in beeld 2026
A8: Projectnaam nieuw | B8: Klant in zicht 2027
A9: Projectnummer nieuw | B9: 30626-0003
A10: Startdatum | B10: 46388
A11: Einddatum | B11: 46752
A13: Projectleider | B13: =_xlfn.XLOOKUP(B6,'report B_Project'!B:B,'report B_Project'!N:N,"niet bekend ") -> Pim de Burger | D13: persnummer | E13: =_xlfn.XLOOKUP(B13,Lijsten!N:N,Lijsten!O:O,"niet bekend") -> 25955
A14: Opdrachtgever | B14: =_xlfn.XLOOKUP(B6,'report B_Project'!B:B,'report B_Project'!P:P,"niet bekend ") -> Roel Bakker | D14: persnummer | E14: =_xlfn.XLOOKUP(B14,Lijsten!Q:Q,Lijsten!R:R,"niet bekend") -> niet bekend
A15: Controller | B15: =_xlfn.XLOOKUP(B6,'report B_Project'!B:B,'report B_Project'!R:R,"niet bekend ") -> George Pavel | D15: persnummer | E15: =_xlfn.XLOOKUP(B15,Lijsten!K:K,Lijsten!L:L,"niet bekend") -> 2061
A16: Handpoc / autopoc | B16: =_xlfn.XLOOKUP(B6,'report B_Project'!B:B,'report B_Project'!S:S,"niet bekend") -> AUT-POC
A18: Projectgroep | B18: Kosten
A19: Kostenplaats | B19: 7040
A20: kostendrager
A21: variant
A22: BTW-code | B22: NL-B
A24: Klantrekening | B24: 10021301
A25: Klantnaam | B25: Cito
A26: Projectcontract | B26: 2000000 | G26: jan | H26: feb | I26: maart | J26: april | K26: mei | L26: juni | M26: juli | N26: aug | O26: sept | P26: okt | Q26: nov | R26: dec | S26: check
F27: Standaardpatroon | G27: =1/12 -> 0.083333333 | H27: =1/12 -> 0.083333333 | I27: =1/12 -> 0.083333333 | J27: =1/12 -> 0.083333333 | K27: =1/12 -> 0.083333333 | L27: =1/12 -> 0.083333333 | M27: =1/12 -> 0.083333333 | N27: =1/12 -> 0.083333333 | ... R27: =1/12 -> 0.083333333 | S27: =SUM(G27:R27) -> 1
A28: Begroting | C28: Maandverdeling | G28: =G27 -> 0.083333333 | H28: =H27 -> 0.083333333 | I28: =I27 -> 0.083333333 | J28: =J27 -> 0.083333333 | K28: =K27 -> 0.083333333 | L28: =L27 -> 0.083333333 | M28: =M27 -> 0.083333333 | N28: =N27 -> 0.083333333 | ... R28: =R27 -> 0.083333333 | S28: =SUM(G28:R28) -> 1
A30: type | B30: code | C30: omschrijving | D30: tarief | E30: Begroting totaal | F30: aantal | G30: jan | H30: feb | I30: maart | J30: april | K30: mei | L30: juni | M30: juli | N30: aug | O30: sept | P30: okt | Q30: nov | R30: dec | S30: check
A31: Eigen medewerkers | B31: AM | C31: Accountmanager | D31: =_xlfn.XLOOKUP(B31,'report B_CategorieBoekjaar'!H:H,'report B_CategorieBoekjaar'!F:F,0) -> 81 | E31: =F31*D31 -> 0 | G31: =$E31*G$28 -> 0 | H31: =$E31*H$28 -> 0 | I31: =$E31*I$28 -> 0 | J31: =$E31*J$28 -> 0 | K31: =$E31*K$28 -> 0 | L31: =$E31*L$28 -> 0 | M31: =$E31*M$28 -> 0 | N31: =$E31*N$28 -> 0 | ... R31: =$E31*R$28 -> 0 | S31: =E31-SUM(G31:R31) -> 0
A32: Eigen medewerkers | B32: BU | C32: Bureauredacteur/documentalist | D32: =_xlfn.XLOOKUP(B32,'report B_CategorieBoekjaar'!H:H,'report B_CategorieBoekjaar'!F:F,0) -> 64 | E32: =F32*D32 -> 0 | G32: =$E32*G$28 -> 0 | H32: =$E32*H$28 -> 0 | I32: =$E32*I$28 -> 0 | J32: =$E32*J$28 -> 0 | K32: =$E32*K$28 -> 0 | L32: =$E32*L$28 -> 0 | M32: =$E32*M$28 -> 0 | N32: =$E32*N$28 -> 0 | ... R32: =$E32*R$28 -> 0 | S32: =E32-SUM(G32:R32) -> 0
A33: Eigen medewerkers | B33: CM | C33: Campagne Marketeer | D33: =_xlfn.XLOOKUP(B33,'report B_CategorieBoekjaar'!H:H,'report B_CategorieBoekjaar'!F:F,0) -> 80 | E33: =F33*D33 -> 0 | G33: =$E33*G$28 -> 0 | H33: =$E33*H$28 -> 0 | I33: =$E33*I$28 -> 0 | J33: =$E33*J$28 -> 0 | K33: =$E33*K$28 -> 0 | L33: =$E33*L$28 -> 0 | M33: =$E33*M$28 -> 0 | N33: =$E33*N$28 -> 0 | ... R33: =$E33*R$28 -> 0 | S33: =E33-SUM(G33:R33) -> 0
A34: Eigen medewerkers | B34: CS | C34: Content Specialist | D34: =_xlfn.XLOOKUP(B34,'report B_CategorieBoekjaar'!H:H,'report B_CategorieBoekjaar'!F:F,0) -> 64 | E34: =F34*D34 -> 0 | G34: =$E34*G$28 -> 0 | H34: =$E34*H$28 -> 0 | I34: =$E34*I$28 -> 0 | J34: =$E34*J$28 -> 0 | K34: =$E34*K$28 -> 0 | L34: =$E34*L$28 -> 0 | M34: =$E34*M$28 -> 0 | N34: =$E34*N$28 -> 0 | ... R34: =$E34*R$28 -> 0 | S34: =E34-SUM(G34:R34) -> 0
A35: Eigen medewerkers | B35: DES | C35: Toetsdeskundige | D35: =_xlfn.XLOOKUP(B35,'report B_CategorieBoekjaar'!H:H,'report B_CategorieBoekjaar'!F:F,0) -> 77 | E35: =F35*D35 -> 0 | G35: =$E35*G$28 -> 0 | H35: =$E35*H$28 -> 0 | I35: =$E35*I$28 -> 0 | J35: =$E35*J$28 -> 0 | K35: =$E35*K$28 -> 0 | L35: =$E35*L$28 -> 0 | M35: =$E35*M$28 -> 0 | N35: =$E35*N$28 -> 0 | ... R35: =$E35*R$28 -> 0 | S35: =E35-SUM(G35:R35) -> 0
A36: Eigen medewerkers | B36: MCB | C36: Medewerker Commerciële Binnendienst | D36: =_xlfn.XLOOKUP(B36,'report B_CategorieBoekjaar'!H:H,'report B_CategorieBoekjaar'!F:F,0) -> 56 | E36: =F36*D36 -> 0 | G36: =$E36*G$28 -> 0 | H36: =$E36*H$28 -> 0 | I36: =$E36*I$28 -> 0 | J36: =$E36*J$28 -> 0 | K36: =$E36*K$28 -> 0 | L36: =$E36*L$28 -> 0 | M36: =$E36*M$28 -> 0 | N36: =$E36*N$28 -> 0 | ... R36: =$E36*R$28 -> 0 | S36: =E36-SUM(G36:R36) -> 0
A37: Eigen medewerkers | B37: MS | C37: Medewerker Media Support | D37: =_xlfn.XLOOKUP(B37,'report B_CategorieBoekjaar'!H:H,'report B_CategorieBoekjaar'!F:F,0) -> 50 | E37: =F37*D37 -> 0 | G37: =$E37*G$28 -> 0 | H37: =$E37*H$28 -> 0 | I37: =$E37*I$28 -> 0 | J37: =$E37*J$28 -> 0 | K37: =$E37*K$28 -> 0 | L37: =$E37*L$28 -> 0 | M37: =$E37*M$28 -> 0 | N37: =$E37*N$28 -> 0 | ... R37: =$E37*R$28 -> 0 | S37: =E37-SUM(G37:R37) -> 0
A38: Eigen medewerkers | B38: PDO | C38: Productowner | D38: =_xlfn.XLOOKUP(B38,'report B_CategorieBoekjaar'!H:H,'report B_CategorieBoekjaar'!F:F,0) -> 87 | E38: =F38*D38 -> 0 | G38: =$E38*G$28 -> 0 | H38: =$E38*H$28 -> 0 | I38: =$E38*I$28 -> 0 | J38: =$E38*J$28 -> 0 | K38: =$E38*K$28 -> 0 | L38: =$E38*L$28 -> 0 | M38: =$E38*M$28 -> 0 | N38: =$E38*N$28 -> 0 | ... R38: =$E38*R$28 -> 0 | S38: =E38-SUM(G38:R38) -> 0
A39: Eigen medewerkers | B39: PRO | C39: Procesondersteuner/procesconsultants | D39: =_xlfn.XLOOKUP(B39,'report B_CategorieBoekjaar'!H:H,'report B_CategorieBoekjaar'!F:F,0) -> 56 | E39: =F39*D39 -> 0 | G39: =$E39*G$28 -> 0 | H39: =$E39*H$28 -> 0 | I39: =$E39*I$28 -> 0 | J39: =$E39*J$28 -> 0 | K39: =$E39*K$28 -> 0 | L39: =$E39*L$28 -> 0 | M39: =$E39*M$28 -> 0 | N39: =$E39*N$28 -> 0 | ... R39: =$E39*R$28 -> 0 | S39: =E39-SUM(G39:R39) -> 0
A40: Eigen medewerkers | B40: PS | C40: Proces Support | D40: =_xlfn.XLOOKUP(B40,'report B_CategorieBoekjaar'!H:H,'report B_CategorieBoekjaar'!F:F,0) -> 46 | E40: =F40*D40 -> 0 | G40: =$E40*G$28 -> 0 | H40: =$E40*H$28 -> 0 | I40: =$E40*I$28 -> 0 | J40: =$E40*J$28 -> 0 | K40: =$E40*K$28 -> 0 | L40: =$E40*L$28 -> 0 | M40: =$E40*M$28 -> 0 | N40: =$E40*N$28 -> 0 | ... R40: =$E40*R$28 -> 0 | S40: =E40-SUM(G40:R40) -> 0
A41: Eigen medewerkers | B41: TOE | C41: Toetsing | D41: =_xlfn.XLOOKUP(B41,'report B_CategorieBoekjaar'!H:H,'report B_CategorieBoekjaar'!F:F,0) -> 63 | E41: =F41*D41 -> 0 | G41: =$E41*G$28 -> 0 | H41: =$E41*H$28 -> 0 | I41: =$E41*I$28 -> 0 | J41: =$E41*J$28 -> 0 | K41: =$E41*K$28 -> 0 | L41: =$E41*L$28 -> 0 | M41: =$E41*M$28 -> 0 | N41: =$E41*N$28 -> 0 | ... R41: =$E41*R$28 -> 0 | S41: =E41-SUM(G41:R41) -> 0
A42: Eigen medewerkers | B42: TOM | C42: Toetsondersteunend medewerker | D42: =_xlfn.XLOOKUP(B42,'report B_CategorieBoekjaar'!H:H,'report B_CategorieBoekjaar'!F:F,0) -> 50 | E42: =F42*D42 -> 0 | G42: =$E42*G$28 -> 0 | H42: =$E42*H$28 -> 0 | I42: =$E42*I$28 -> 0 | J42: =$E42*J$28 -> 0 | K42: =$E42*K$28 -> 0 | L42: =$E42*L$28 -> 0 | M42: =$E42*M$28 -> 0 | N42: =$E42*N$28 -> 0 | ... R42: =$E42*R$28 -> 0 | S42: =E42-SUM(G42:R42) -> 0
... A54: Eigen medewerkers | B54: PJM | C54: Projectmanager | D54: =_xlfn.XLOOKUP(B54,'report B_CategorieBoekjaar'!H:H,'report B_CategorieBoekjaar'!F:F,0) -> 90 | E54: =F54*D54 -> 0 | G54: =$E54*G$28 -> 0 | H54: =$E54*H$28 -> 0 | I54: =$E54*I$28 -> 0 | J54: =$E54*J$28 -> 0 | K54: =$E54*K$28 -> 0 | L54: =$E54*L$28 -> 0 | M54: =$E54*M$28 -> 0 | N54: =$E54*N$28 -> 0 | ... R54: =$E54*R$28 -> 0 | S54: =E54-SUM(G54:R54) -> 0
A55: Inleen medewerkers | B55: DES | C55: =_xlfn.XLOOKUP(B55,$B$31:$B$54,$C$31:$C$54,0) -> Toetsdeskundige | D55: =_xlfn.XLOOKUP(B55,'report B_CategorieBoekjaar'!I:I,'report B_CategorieBoekjaar'!G:G,0) -> 109 | E55: =F55*D55 -> 0 | G55: =$E55*G$28 -> 0 | H55: =$E55*H$28 -> 0 | I55: =$E55*I$28 -> 0 | J55: =$E55*J$28 -> 0 | K55: =$E55*K$28 -> 0 | L55: =$E55*L$28 -> 0 | M55: =$E55*M$28 -> 0 | N55: =$E55*N$28 -> 0 | ... R55: =$E55*R$28 -> 0 | S55: =E55-SUM(G55:R55) -> 0
A56: Inleen medewerkers | B56: EA | C56: =_xlfn.XLOOKUP(B56,$B$31:$B$54,$C$31:$C$54,0) -> Enterprise Architect | D56: =_xlfn.XLOOKUP(B56,'report B_CategorieBoekjaar'!I:I,'report B_CategorieBoekjaar'!G:G,0) -> 116 | E56: =F56*D56 -> 0 | G56: =$E56*G$28 -> 0 | H56: =$E56*H$28 -> 0 | I56: =$E56*I$28 -> 0 | J56: =$E56*J$28 -> 0 | K56: =$E56*K$28 -> 0 | L56: =$E56*L$28 -> 0 | M56: =$E56*M$28 -> 0 | N56: =$E56*N$28 -> 0 | ... R56: =$E56*R$28 -> 0 | S56: =E56-SUM(G56:R56) -> 0
A57: Inleen medewerkers | B57: FUB | C57: =_xlfn.XLOOKUP(B57,$B$31:$B$54,$C$31:$C$54,0) -> Functioneel Beheerder | D57: =_xlfn.XLOOKUP(B57,'report B_CategorieBoekjaar'!I:I,'report B_CategorieBoekjaar'!G:G,0) -> 102 | E57: =F57*D57 -> 0 | G57: =$E57*G$28 -> 0 | H57: =$E57*H$28 -> 0 | I57: =$E57*I$28 -> 0 | J57: =$E57*J$28 -> 0 | K57: =$E57*K$28 -> 0 | L57: =$E57*L$28 -> 0 | M57: =$E57*M$28 -> 0 | N57: =$E57*N$28 -> 0 | ... R57: =$E57*R$28 -> 0 | S57: =E57-SUM(G57:R57) -> 0
A58: Inleen medewerkers | B58: IA | C58: =_xlfn.XLOOKUP(B58,$B$31:$B$54,$C$31:$C$54,0) -> Businessanalist | D58: =_xlfn.XLOOKUP(B58,'report B_CategorieBoekjaar'!I:I,'report B_CategorieBoekjaar'!G:G,0) -> 101 | E58: =F58*D58 -> 0 | G58: =$E58*G$28 -> 0 | H58: =$E58*H$28 -> 0 | I58: =$E58*I$28 -> 0 | J58: =$E58*J$28 -> 0 | K58: =$E58*K$28 -> 0 | L58: =$E58*L$28 -> 0 | M58: =$E58*M$28 -> 0 | N58: =$E58*N$28 -> 0 | ... R58: =$E58*R$28 -> 0 | S58: =E58-SUM(G58:R58) -> 0
A59: Inleen medewerkers | B59: ICTB | C59: =_xlfn.XLOOKUP(B59,$B$31:$B$54,$C$31:$C$54,0) -> ICT Beheerder | D59: =_xlfn.XLOOKUP(B59,'report B_CategorieBoekjaar'!I:I,'report B_CategorieBoekjaar'!G:G,0) -> 96 | E59: =F59*D59 -> 0 | G59: =$E59*G$28 -> 0 | H59: =$E59*H$28 -> 0 | I59: =$E59*I$28 -> 0 | J59: =$E59*J$28 -> 0 | K59: =$E59*K$28 -> 0 | L59: =$E59*L$28 -> 0 | M59: =$E59*M$28 -> 0 | N59: =$E59*N$28 -> 0 | ... R59: =$E59*R$28 -> 0 | S59: =E59-SUM(G59:R59) -> 0
A60: Inleen medewerkers | B60: ICTE | C60: =_xlfn.XLOOKUP(B60,$B$31:$B$54,$C$31:$C$54,0) -> ICT medewerker Extern | D60: =_xlfn.XLOOKUP(B60,'report B_CategorieBoekjaar'!I:I,'report B_CategorieBoekjaar'!G:G,0) -> 139 | E60: =F60*D60 -> 0 | G60: =$E60*G$28 -> 0 | H60: =$E60*H$28 -> 0 | I60: =$E60*I$28 -> 0 | J60: =$E60*J$28 -> 0 | K60: =$E60*K$28 -> 0 | L60: =$E60*L$28 -> 0 | M60: =$E60*M$28 -> 0 | N60: =$E60*N$28 -> 0 | ... R60: =$E60*R$28 -> 0 | S60: =E60-SUM(G60:R60) -> 0
A61: Inleen medewerkers | B61: ICTO | C61: =_xlfn.XLOOKUP(B61,$B$31:$B$54,$C$31:$C$54,0) -> ICT Ontwikkelaar | D61: =_xlfn.XLOOKUP(B61,'report B_CategorieBoekjaar'!I:I,'report B_CategorieBoekjaar'!G:G,0) -> 100 | E61: =F61*D61 -> 0 | G61: =$E61*G$28 -> 0 | H61: =$E61*H$28 -> 0 | I61: =$E61*I$28 -> 0 | J61: =$E61*J$28 -> 0 | K61: =$E61*K$28 -> 0 | L61: =$E61*L$28 -> 0 | M61: =$E61*M$28 -> 0 | N61: =$E61*N$28 -> 0 | ... R61: =$E61*R$28 -> 0 | S61: =E61-SUM(G61:R61) -> 0
A62: Inleen medewerkers | B62: PJM | C62: =_xlfn.XLOOKUP(B62,$B$31:$B$54,$C$31:$C$54,0) -> Projectmanager | D62: =_xlfn.XLOOKUP(B62,'report B_CategorieBoekjaar'!I:I,'report B_CategorieBoekjaar'!G:G,0) -> 122 | E62: =F62*D62 -> 0 | G62: =$E62*G$28 -> 0 | H62: =$E62*H$28 -> 0 | I62: =$E62*I$28 -> 0 | J62: =$E62*J$28 -> 0 | K62: =$E62*K$28 -> 0 | L62: =$E62*L$28 -> 0 | M62: =$E62*M$28 -> 0 | N62: =$E62*N$28 -> 0 | ... R62: =$E62*R$28 -> 0 | S62: =E62-SUM(G62:R62) -> 0
A63: Inleen medewerkers | B63: WO | C63: =_xlfn.XLOOKUP(B63,$B$31:$B$54,$C$31:$C$54,0) -> Wetenschappelijk onderzoeker | D63: =_xlfn.XLOOKUP(B63,'report B_CategorieBoekjaar'!I:I,'report B_CategorieBoekjaar'!G:G,0) -> 120 | E63: =F63*D63 -> 0 | G63: =$E63*G$28 -> 0 | H63: =$E63*H$28 -> 0 | I63: =$E63*I$28 -> 0 | J63: =$E63*J$28 -> 0 | K63: =$E63*K$28 -> 0 | L63: =$E63*L$28 -> 0 | M63: =$E63*M$28 -> 0 | N63: =$E63*N$28 -> 0 | ... R63: =$E63*R$28 -> 0 | S63: =E63-SUM(G63:R63) -> 0
A64: Inleen medewerkers | B64: PRO | C64: =_xlfn.XLOOKUP(B64,$B$31:$B$54,$C$31:$C$54,0) -> Procesondersteuner/procesconsultants | D64: =_xlfn.XLOOKUP(B64,'report B_CategorieBoekjaar'!I:I,'report B_CategorieBoekjaar'!G:G,0) -> 88 | E64: =F64*D64 -> 0 | G64: =$E64*G$28 -> 0 | H64: =$E64*H$28 -> 0 | I64: =$E64*I$28 -> 0 | J64: =$E64*J$28 -> 0 | K64: =$E64*K$28 -> 0 | L64: =$E64*L$28 -> 0 | M64: =$E64*M$28 -> 0 | N64: =$E64*N$28 -> 0 | ... R64: =$E64*R$28 -> 0 | S64: =E64-SUM(G64:R64) -> 0
A65: Inleen medewerkers | B65: TOM | C65: =_xlfn.XLOOKUP(B65,$B$31:$B$54,$C$31:$C$54,0) -> Toetsondersteunend medewerker | D65: =_xlfn.XLOOKUP(B65,'report B_CategorieBoekjaar'!I:I,'report B_CategorieBoekjaar'!G:G,0) -> 82 | E65: =F65*D65 -> 0 | G65: =$E65*G$28 -> 0 | H65: =$E65*H$28 -> 0 | I65: =$E65*I$28 -> 0 | J65: =$E65*J$28 -> 0 | K65: =$E65*K$28 -> 0 | L65: =$E65*L$28 -> 0 | M65: =$E65*M$28 -> 0 | N65: =$E65*N$28 -> 0 | ... R65: =$E65*R$28 -> 0 | S65: =E65-SUM(G65:R65) -> 0
A66: Onkosten | B66: =LEFT(C66,3) -> 310 | C66: 310 - Zaalhuur en Catering (extern) | D66: 0 | E66: =F66*D66 -> 0 | F66: 1 | G66: =$E66*G$28 -> 0 | H66: =$E66*H$28 -> 0 | I66: =$E66*I$28 -> 0 | J66: =$E66*J$28 -> 0 | K66: =$E66*K$28 -> 0 | L66: =$E66*L$28 -> 0 | M66: =$E66*M$28 -> 0 | N66: =$E66*N$28 -> 0 | ... R66: =$E66*R$28 -> 0 | S66: =E66-SUM(G66:R66) -> 0
A67: Onkosten | B67: =LEFT(C67,3) -> 350 | C67: 350 - ICT hardware en software | E67: =F67*D67 -> 0 | F67: 1 | G67: =$E67*G$28 -> 0 | H67: =$E67*H$28 -> 0 | I67: =$E67*I$28 -> 0 | J67: =$E67*J$28 -> 0 | K67: =$E67*K$28 -> 0 | L67: =$E67*L$28 -> 0 | M67: =$E67*M$28 -> 0 | N67: =$E67*N$28 -> 0 | ... R67: =$E67*R$28 -> 0 | S67: =E67-SUM(G67:R67) -> 0
A68: Onkosten | B68: =LEFT(C68,3) -> 410 | C68: 410 - Advies en Consultant | E68: =F68*D68 -> 0 | F68: 1 | G68: =$E68*G$28 -> 0 | H68: =$E68*H$28 -> 0 | I68: =$E68*I$28 -> 0 | J68: =$E68*J$28 -> 0 | K68: =$E68*K$28 -> 0 | L68: =$E68*L$28 -> 0 | M68: =$E68*M$28 -> 0 | N68: =$E68*N$28 -> 0 | ... R68: =$E68*R$28 -> 0 | S68: =E68-SUM(G68:R68) -> 0
A69: Onkosten | B69: =LEFT(C69,3) -> 470 | C69: 470 - Internet en Telecommunicatie | D69: 0 | E69: =F69*D69 -> 0 | F69: 1 | G69: =$E69*G$28 -> 0 | H69: =$E69*H$28 -> 0 | I69: =$E69*I$28 -> 0 | J69: =$E69*J$28 -> 0 | K69: =$E69*K$28 -> 0 | L69: =$E69*L$28 -> 0 | M69: =$E69*M$28 -> 0 | N69: =$E69*N$28 -> 0 | ... R69: =$E69*R$28 -> 0 | S69: =E69-SUM(G69:R69) -> 0
A70: Onkosten | B70: =LEFT(C70,3) -> 490 | C70: 490 - Kantoorbenodigdheden | D70: 0 | E70: =F70*D70 -> 0 | F70: 1 | G70: =$E70*G$28 -> 0 | H70: =$E70*H$28 -> 0 | I70: =$E70*I$28 -> 0 | J70: =$E70*J$28 -> 0 | K70: =$E70*K$28 -> 0 | L70: =$E70*L$28 -> 0 | M70: =$E70*M$28 -> 0 | N70: =$E70*N$28 -> 0 | ... R70: =$E70*R$28 -> 0 | S70: =E70-SUM(G70:R70) -> 0
A71: Onkosten | B71: =LEFT(C71,3) -> 491 | C71: 491 - Lidmaatschappen, inschrijvingen en documentatie abonnementen | D71: 0 | E71: =F71*D71 -> 0 | F71: 1 | G71: =$E71*G$28 -> 0 | H71: =$E71*H$28 -> 0 | I71: =$E71*I$28 -> 0 | J71: =$E71*J$28 -> 0 | K71: =$E71*K$28 -> 0 | L71: =$E71*L$28 -> 0 | M71: =$E71*M$28 -> 0 | N71: =$E71*N$28 -> 0 | ... R71: =$E71*R$28 -> 0 | S71: =E71-SUM(G71:R71) -> 0
A72: Onkosten | B72: =LEFT(C72,3) -> 510 | C72: 510 - Verzendkosten | D72: 0 | E72: =F72*D72 -> 0 | F72: 1 | G72: =$E72*G$28 -> 0 | H72: =$E72*H$28 -> 0 | I72: =$E72*I$28 -> 0 | J72: =$E72*J$28 -> 0 | K72: =$E72*K$28 -> 0 | L72: =$E72*L$28 -> 0 | M72: =$E72*M$28 -> 0 | N72: =$E72*N$28 -> 0 | ... R72: =$E72*R$28 -> 0 | S72: =E72-SUM(G72:R72) -> 0
A73: Onkosten | B73: =LEFT(C73,3) -> 520 | C73: 520 - Drukwerk en verpakkingen | D73: 0 | E73: =F73*D73 -> 0 | F73: 1 | G73: =$E73*G$28 -> 0 | H73: =$E73*H$28 -> 0 | I73: =$E73*I$28 -> 0 | J73: =$E73*J$28 -> 0 | K73: =$E73*K$28 -> 0 | L73: =$E73*L$28 -> 0 | M73: =$E73*M$28 -> 0 | N73: =$E73*N$28 -> 0 | ... R73: =$E73*R$28 -> 0 | S73: =E73-SUM(G73:R73) -> 0
A74: Onkosten | B74: =LEFT(C74,3) -> 542 | C74: 542 - Multimedia(re)producties | D74: 0 | E74: =F74*D74 -> 0 | F74: 1 | G74: =$E74*G$28 -> 0 | H74: =$E74*H$28 -> 0 | I74: =$E74*I$28 -> 0 | J74: =$E74*J$28 -> 0 | K74: =$E74*K$28 -> 0 | L74: =$E74*L$28 -> 0 | M74: =$E74*M$28 -> 0 | N74: =$E74*N$28 -> 0 | ... R74: =$E74*R$28 -> 0 | S74: =E74-SUM(G74:R74) -> 0
A75: Onkosten | B75: =LEFT(C75,3) -> 543 | C75: 543 - ICT diensten | E75: =F75*D75 -> 0 | F75: 1 | G75: =$E75*G$28 -> 0 | H75: =$E75*H$28 -> 0 | I75: =$E75*I$28 -> 0 | J75: =$E75*J$28 -> 0 | K75: =$E75*K$28 -> 0 | L75: =$E75*L$28 -> 0 | M75: =$E75*M$28 -> 0 | N75: =$E75*N$28 -> 0 | ... R75: =$E75*R$28 -> 0 | S75: =E75-SUM(G75:R75) -> 0
A76: Onkosten | B76: =LEFT(C76,3) -> 560 | C76: 560 - Examen- en itemconstructie (niet cg) | D76: 0 | E76: =F76*D76 -> 0 | F76: 1 | G76: =$E76*G$28 -> 0 | H76: =$E76*H$28 -> 0 | I76: =$E76*I$28 -> 0 | J76: =$E76*J$28 -> 0 | K76: =$E76*K$28 -> 0 | L76: =$E76*L$28 -> 0 | M76: =$E76*M$28 -> 0 | N76: =$E76*N$28 -> 0 | ... R76: =$E76*R$28 -> 0 | S76: =E76-SUM(G76:R76) -> 0
A77: Onkosten | B77: =LEFT(C77,3) -> 562 | C77: 562 - Examenbegeleiders, surveillanten | D77: 0 | E77: =F77*D77 -> 0 | F77: 1 | G77: =$E77*G$28 -> 0 | H77: =$E77*H$28 -> 0 | I77: =$E77*I$28 -> 0 | J77: =$E77*J$28 -> 0 | K77: =$E77*K$28 -> 0 | L77: =$E77*L$28 -> 0 | M77: =$E77*M$28 -> 0 | N77: =$E77*N$28 -> 0 | ... R77: =$E77*R$28 -> 0 | S77: =E77-SUM(G77:R77) -> 0
A78: Onkosten | B78: =LEFT(C78,3) -> 563 | C78: 563 - Correctiewerk (correctoren) | D78: 0 | E78: =F78*D78 -> 0 | F78: 1 | G78: =$E78*G$28 -> 0 | H78: =$E78*H$28 -> 0 | I78: =$E78*I$28 -> 0 | J78: =$E78*J$28 -> 0 | K78: =$E78*K$28 -> 0 | L78: =$E78*L$28 -> 0 | M78: =$E78*M$28 -> 0 | N78: =$E78*N$28 -> 0 | ... R78: =$E78*R$28 -> 0 | S78: =E78-SUM(G78:R78) -> 0
A79: Onkosten | B79: =LEFT(C79,3) -> 566 | C79: 566 - Examenconstructie / CG leden | D79: 0 | E79: =F79*D79 -> 0 | F79: 1 | G79: =$E79*G$28 -> 0 | H79: =$E79*H$28 -> 0 | I79: =$E79*I$28 -> 0 | J79: =$E79*J$28 -> 0 | K79: =$E79*K$28 -> 0 | L79: =$E79*L$28 -> 0 | M79: =$E79*M$28 -> 0 | N79: =$E79*N$28 -> 0 | ... R79: =$E79*R$28 -> 0 | S79: =E79-SUM(G79:R79) -> 0
A80: Onkosten | B80: =LEFT(C80,3) -> 567 | C80: 567 - Examencentra | D80: 0 | E80: =F80*D80 -> 0 | F80: 1 | G80: =$E80*G$28 -> 0 | H80: =$E80*H$28 -> 0 | I80: =$E80*I$28 -> 0 | J80: =$E80*J$28 -> 0 | K80: =$E80*K$28 -> 0 | L80: =$E80*L$28 -> 0 | M80: =$E80*M$28 -> 0 | N80: =$E80*N$28 -> 0 | ... R80: =$E80*R$28 -> 0 | S80: =E80-SUM(G80:R80) -> 0
A81: Onkosten | B81: =LEFT(C81,3) -> 568 | C81: 568 - Assessoren | D81: 0 | E81: =F81*D81 -> 0 | F81: 1 | G81: =$E81*G$28 -> 0 | H81: =$E81*H$28 -> 0 | I81: =$E81*I$28 -> 0 | J81: =$E81*J$28 -> 0 | K81: =$E81*K$28 -> 0 | L81: =$E81*L$28 -> 0 | M81: =$E81*M$28 -> 0 | N81: =$E81*N$28 -> 0 | ... R81: =$E81*R$28 -> 0 | S81: =E81-SUM(G81:R81) -> 0
A82: Onkosten | B82: =LEFT(C82,3) -> 580 | C82: 580 - Vertaalwerk en tekstschrijvers | D82: 0 | E82: =F82*D82 -> 0 | F82: 1 | G82: =$E82*G$28 -> 0 | H82: =$E82*H$28 -> 0 | I82: =$E82*I$28 -> 0 | J82: =$E82*J$28 -> 0 | K82: =$E82*K$28 -> 0 | L82: =$E82*L$28 -> 0 | M82: =$E82*M$28 -> 0 | N82: =$E82*N$28 -> 0 | ... R82: =$E82*R$28 -> 0 | S82: =E82-SUM(G82:R82) -> 0
A83: Onkosten | B83: =LEFT(C83,3) -> 582 | C83: 582 - Teken-, grafisch en fotowerk | D83: 0 | E83: =F83*D83 -> 0 | F83: 1 | G83: =$E83*G$28 -> 0 | H83: =$E83*H$28 -> 0 | I83: =$E83*I$28 -> 0 | J83: =$E83*J$28 -> 0 | K83: =$E83*K$28 -> 0 | L83: =$E83*L$28 -> 0 | M83: =$E83*M$28 -> 0 | N83: =$E83*N$28 -> 0 | ... R83: =$E83*R$28 -> 0 | S83: =E83-SUM(G83:R83) -> 0
A84: Onkosten | B84: =LEFT(C84,3) -> 585 | C84: 585 - Marktonderzoek | D84: 0 | E84: =F84*D84 -> 0 | F84: 1 | G84: =$E84*G$28 -> 0 | H84: =$E84*H$28 -> 0 | I84: =$E84*I$28 -> 0 | J84: =$E84*J$28 -> 0 | K84: =$E84*K$28 -> 0 | L84: =$E84*L$28 -> 0 | M84: =$E84*M$28 -> 0 | N84: =$E84*N$28 -> 0 | ... R84: =$E84*R$28 -> 0 | S84: =E84-SUM(G84:R84) -> 0
A85: Onkosten | B85: =LEFT(C85,3) -> 586 | C85: 586 - Trainers/Docenten | D85: 0 | E85: =F85*D85 -> 0 | F85: 1 | G85: =$E85*G$28 -> 0 | H85: =$E85*H$28 -> 0 | I85: =$E85*I$28 -> 0 | J85: =$E85*J$28 -> 0 | K85: =$E85*K$28 -> 0 | L85: =$E85*L$28 -> 0 | M85: =$E85*M$28 -> 0 | N85: =$E85*N$28 -> 0 | ... R85: =$E85*R$28 -> 0 | S85: =E85-SUM(G85:R85) -> 0
A86: Onkosten | B86: =LEFT(C86,3) -> 610 | C86: 610 - Citorant (doorberekend) | D86: 0 | E86: =F86*D86 -> 0 | F86: 1 | G86: =$E86*G$28 -> 0 | H86: =$E86*H$28 -> 0 | I86: =$E86*I$28 -> 0 | J86: =$E86*J$28 -> 0 | K86: =$E86*K$28 -> 0 | L86: =$E86*L$28 -> 0 | M86: =$E86*M$28 -> 0 | N86: =$E86*N$28 -> 0 | ... R86: =$E86*R$28 -> 0 | S86: =E86-SUM(G86:R86) -> 0
A87: Onkosten | B87: =LEFT(C87,3) -> 630 | C87: 630 - Reis en verblijfskosten eigen medewerkers | D87: 0 | E87: =F87*D87 -> 0 | F87: 1 | G87: =$E87*G$28 -> 0 | H87: =$E87*H$28 -> 0 | I87: =$E87*I$28 -> 0 | J87: =$E87*J$28 -> 0 | K87: =$E87*K$28 -> 0 | L87: =$E87*L$28 -> 0 | M87: =$E87*M$28 -> 0 | N87: =$E87*N$28 -> 0 | ... R87: =$E87*R$28 -> 0 | S87: =E87-SUM(G87:R87) -> 0
... A94: Onkosten | B94: =LEFT(C94,3) -> 710 | C94: 710 - Centraal kopieren Zwart Wit | D94: 0.05 | E94: =F94*D94 -> 0 | F94: 0 | G94: =$E94*G$28 -> 0 | H94: =$E94*H$28 -> 0 | I94: =$E94*I$28 -> 0 | J94: =$E94*J$28 -> 0 | K94: =$E94*K$28 -> 0 | L94: =$E94*L$28 -> 0 | M94: =$E94*M$28 -> 0 | N94: =$E94*N$28 -> 0 | ... R94: =$E94*R$28 -> 0 | S94: =E94-SUM(G94:R94) -> 0
A95: Onkosten | B95: =LEFT(C95,3) -> 720 | C95: 720 - Centraal kopieren kleur | D95: 0.3 | E95: =F95*D95 -> 0 | G95: =$E95*G$28 -> 0 | H95: =$E95*H$28 -> 0 | I95: =$E95*I$28 -> 0 | J95: =$E95*J$28 -> 0 | K95: =$E95*K$28 -> 0 | L95: =$E95*L$28 -> 0 | M95: =$E95*M$28 -> 0 | N95: =$E95*N$28 -> 0 | ... R95: =$E95*R$28 -> 0 | S95: =E95-SUM(G95:R95) -> 0
A96: Onkosten | B96: =LEFT(C96,3) -> 730 | C96: 730 - Optisch lezen | D96: 0.05 | E96: =F96*D96 -> 0 | G96: =$E96*G$28 -> 0 | H96: =$E96*H$28 -> 0 | I96: =$E96*I$28 -> 0 | J96: =$E96*J$28 -> 0 | K96: =$E96*K$28 -> 0 | L96: =$E96*L$28 -> 0 | M96: =$E96*M$28 -> 0 | N96: =$E96*N$28 -> 0 | ... R96: =$E96*R$28 -> 0 | S96: =E96-SUM(G96:R96) -> 0
A97: Onkosten | B97: =LEFT(C97,3) -> 740 | C97: 740 - Artikel verbruik | D97: 0 | E97: =F97*D97 -> 0 | F97: 1 | G97: =$E97*G$28 -> 0 | H97: =$E97*H$28 -> 0 | I97: =$E97*I$28 -> 0 | J97: =$E97*J$28 -> 0 | K97: =$E97*K$28 -> 0 | L97: =$E97*L$28 -> 0 | M97: =$E97*M$28 -> 0 | N97: =$E97*N$28 -> 0 | ... R97: =$E97*R$28 -> 0 | S97: =E97-SUM(G97:R97) -> 0
A98: Omzet | B98: 843 | C98: Omzet | E98: =F98*D98 -> 0 | F98: 1 | G98: =($E$98/SUM($E$31:$E$97))*SUM(G31:G97) -> #DIV/0! | H98: =($E$98/SUM($E$31:$E$97))*SUM(H31:H97) -> #DIV/0! | I98: =($E$98/SUM($E$31:$E$97))*SUM(I31:I97) -> #DIV/0! | J98: =($E$98/SUM($E$31:$E$97))*SUM(J31:J97) -> #DIV/0! | K98: =($E$98/SUM($E$31:$E$97))*SUM(K31:K97) -> #DIV/0! | L98: =($E$98/SUM($E$31:$E$97))*SUM(L31:L97) -> #DIV/0! | M98: =($E$98/SUM($E$31:$E$97))*SUM(M31:M97) -> #DIV/0! | N98: =($E$98/SUM($E$31:$E$97))*SUM(N31:N97) -> #DIV/0! | ... R98: =($E$98/SUM($E$31:$E$97))*SUM(R31:R97) -> #DIV/0! | S98: =E98-SUM(G98:R98) -> #DIV/0!
C100: Eigen medewerkers | E100: =SUMIF($A$31:$A$98,$C100,E$31:E$98) -> 0 | F100: =SUMIF($A$31:$A$98,$C100,F$31:F$98) -> 0 | G100: =SUMIF($A$31:$A$98,$C100,G$31:G$98) -> 0 | H100: =SUMIF($A$31:$A$98,$C100,H$31:H$98) -> 0 | I100: =SUMIF($A$31:$A$98,$C100,I$31:I$98) -> 0 | J100: =SUMIF($A$31:$A$98,$C100,J$31:J$98) -> 0 | K100: =SUMIF($A$31:$A$98,$C100,K$31:K$98) -> 0 | L100: =SUMIF($A$31:$A$98,$C100,L$31:L$98) -> 0 | ... R100: =SUMIF($A$31:$A$98,$C100,R$31:R$98) -> 0 | S100: =E100-SUM(G100:R100) -> 0
C101: inleen medewerkers | E101: =SUMIF($A$31:$A$98,$C101,E$31:E$98) -> 0 | F101: =SUMIF($A$31:$A$98,$C101,F$31:F$98) -> 0 | G101: =SUMIF($A$31:$A$98,$C101,G$31:G$98) -> 0 | H101: =SUMIF($A$31:$A$98,$C101,H$31:H$98) -> 0 | I101: =SUMIF($A$31:$A$98,$C101,I$31:I$98) -> 0 | J101: =SUMIF($A$31:$A$98,$C101,J$31:J$98) -> 0 | K101: =SUMIF($A$31:$A$98,$C101,K$31:K$98) -> 0 | L101: =SUMIF($A$31:$A$98,$C101,L$31:L$98) -> 0 | ... R101: =SUMIF($A$31:$A$98,$C101,R$31:R$98) -> 0 | S101: =E101-SUM(G101:R101) -> 0
C102: Onkosten | E102: =SUMIF($A$31:$A$98,$C102,E$31:E$98) -> 0 | G102: =SUMIF($A$31:$A$98,$C102,G$31:G$98) -> 0 | H102: =SUMIF($A$31:$A$98,$C102,H$31:H$98) -> 0 | I102: =SUMIF($A$31:$A$98,$C102,I$31:I$98) -> 0 | J102: =SUMIF($A$31:$A$98,$C102,J$31:J$98) -> 0 | K102: =SUMIF($A$31:$A$98,$C102,K$31:K$98) -> 0 | L102: =SUMIF($A$31:$A$98,$C102,L$31:L$98) -> 0 | M102: =SUMIF($A$31:$A$98,$C102,M$31:M$98) -> 0 | N102: =SUMIF($A$31:$A$98,$C102,N$31:N$98) -> 0 | ... R102: =SUMIF($A$31:$A$98,$C102,R$31:R$98) -> 0 | S102: =E102-SUM(G102:R102) -> 0
C103: Omzet | E103: =SUMIF($A$31:$A$98,$C103,E$31:E$98) -> 0 | G103: =SUMIF($A$31:$A$98,$C103,G$31:G$98) -> #DIV/0! | H103: =SUMIF($A$31:$A$98,$C103,H$31:H$98) -> #DIV/0! | I103: =SUMIF($A$31:$A$98,$C103,I$31:I$98) -> #DIV/0! | J103: =SUMIF($A$31:$A$98,$C103,J$31:J$98) -> #DIV/0! | K103: =SUMIF($A$31:$A$98,$C103,K$31:K$98) -> #DIV/0! | L103: =SUMIF($A$31:$A$98,$C103,L$31:L$98) -> #DIV/0! | M103: =SUMIF($A$31:$A$98,$C103,M$31:M$98) -> #DIV/0! | N103: =SUMIF($A$31:$A$98,$C103,N$31:N$98) -> #DIV/0! | ... R103: =SUMIF($A$31:$A$98,$C103,R$31:R$98) -> #DIV/0! | S103: =E103-SUM(G103:R103) -> #DIV/0!
C104: Projectresultaat | E104: =E103-E100-E101-E102 -> 0 | F104: =SUM(F100:F103) -> 0 | G104: =G98-SUM(G31:G97) -> #DIV/0! | H104: =H98-SUM(H31:H97) -> #DIV/0! | I104: =I98-SUM(I31:I97) -> #DIV/0! | J104: =J98-SUM(J31:J97) -> #DIV/0! | K104: =K98-SUM(K31:K97) -> #DIV/0! | L104: =L98-SUM(L31:L97) -> #DIV/0! | M104: =M98-SUM(M31:M97) -> #DIV/0! | N104: =N98-SUM(N31:N97) -> #DIV/0! | ... R104: =R98-SUM(R31:R97) -> #DIV/0! | S104: =E104-SUM(G104:R104) -> #DIV/0!
C105: Marge | E105: =E104/E103 -> #DIV/0!
C108: Controle tabblad ETC regels projecten | E108: =SUM('ETC regels projecten'!$K:$K)-SUM(Projectbegroting!E31:E98) -> 0 | F108: =SUM(F30:F97)-SUM('ETC regels projecten'!I:I) -> -1
C109: Controle tabblad probuto | E109: =E104+SUM(Probuto!E2:P8) -> 0 | G109: =G104+SUM(Probuto!E$2:E$8) -> #DIV/0! | H109: =H104+SUM(Probuto!F$2:F$8) -> #DIV/0! | I109: =I104+SUM(Probuto!G$2:G$8) -> #DIV/0! | J109: =J104+SUM(Probuto!H$2:H$8) -> #DIV/0! | K109: =K104+SUM(Probuto!I$2:I$8) -> #DIV/0! | L109: =L104+SUM(Probuto!J$2:J$8) -> #DIV/0! | M109: =M104+SUM(Probuto!K$2:K$8) -> #DIV/0! | N109: =N104+SUM(Probuto!L$2:L$8) -> #DIV/0! | ... R109: =R104+SUM(Probuto!P$2:P$8) -> #DIV/0!

Sheet Stamgegevens projecten
A1: projectnaam | B1: projectnummer | C1: ingangsdatum | D1: einddatum | E1: koptekst project | F1: vertaling projectgroep | G1: vertaling PL | H1: vertaling controller | I1: vertaling verkoopleider | J1: klantrekening | K1: klantnaam | L1: projectcontract | M1: Dimensie | N1: BTW | O1: sorteerveld 1 | P1: sorteerveld 2 | Q1: sorteerveld 3 | R1: projectnaam
A2: =Projectbegroting!$B$8 -> Klant in zicht 2027 | B2: =Projectbegroting!$B$9 -> 30626-0003 | C2: =Projectbegroting!B10 -> 46388 | D2: =Projectbegroting!B11 -> 46752 | E2: No | F2: =Projectbegroting!B18 -> Kosten | G2: 41265 | H2: 42805 | I2: 34955 | J2: =Projectbegroting!B24 -> 10021301 | K2: =Projectbegroting!B25 -> Cito | L2: =Projectbegroting!B26 -> 2000000 | M2: ="-"&Projectbegroting!B19&"-"&Projectbegroting!B20&"-"&Projectbegroting!B21&"-"&Projectbegroting!B9&"-" -> -7040---30626-0003- | N2: =Projectbegroting!B22 -> NL-B | O2: =Projectbegroting!B16 -> AUT-POC | R2: =Projectbegroting!$B$8 -> Klant in zicht 2027
A7: * Let op als er geen hoofdproject is dan ook een hoofdproject op dit overzicht meenemen (dus geen projectnummers vorig jaar).

Sheet ETC regels projecten
A1: hulpkolom | C1: Projectnaam | D1: AXnr | E1: Meerjarig | F1: Omzet | G1: Opmerkingen | H1: Categorie | I1: Aantal | J1: Prijs | K1: Bedrag
A2: =CONCATENATE(D2,H2) -> 30626-0003AM | C2: =Projectbegroting!$B$8 -> Klant in zicht 2027 | D2: =Projectbegroting!$B$9 -> 30626-0003 | H2: AM | I2: =Projectbegroting!F31 -> 0 | J2: =Projectbegroting!D31 -> 81 | K2: =Projectbegroting!E31 -> 0
A3: =CONCATENATE(D3,H3) -> 30626-0003BU | C3: =Projectbegroting!$B$8 -> Klant in zicht 2027 | D3: =Projectbegroting!$B$9 -> 30626-0003 | H3: BU | I3: =Projectbegroting!F32 -> 0 | J3: =Projectbegroting!D32 -> 64 | K3: =Projectbegroting!E32 -> 0
A4: =CONCATENATE(D4,H4) -> 30626-0003CM | C4: =Projectbegroting!$B$8 -> Klant in zicht 2027 | D4: =Projectbegroting!$B$9 -> 30626-0003 | H4: CM | I4: =Projectbegroting!F33 -> 0 | J4: =Projectbegroting!D33 -> 80 | K4: =Projectbegroting!E33 -> 0
A5: =CONCATENATE(D5,H5) -> 30626-0003CS | C5: =Projectbegroting!$B$8 -> Klant in zicht 2027 | D5: =Projectbegroting!$B$9 -> 30626-0003 | H5: CS | I5: =Projectbegroting!F34 -> 0 | J5: =Projectbegroting!D34 -> 64 | K5: =Projectbegroting!E34 -> 0
A6: =CONCATENATE(D6,H6) -> 30626-0003DES | C6: =Projectbegroting!$B$8 -> Klant in zicht 2027 | D6: =Projectbegroting!$B$9 -> 30626-0003 | H6: DES | I6: =Projectbegroting!F35 -> 0 | J6: =Projectbegroting!D35 -> 77 | K6: =Projectbegroting!E35 -> 0
A7: =CONCATENATE(D7,H7) -> 30626-0003MCB | C7: =Projectbegroting!$B$8 -> Klant in zicht 2027 | D7: =Projectbegroting!$B$9 -> 30626-0003 | H7: MCB | I7: =Projectbegroting!F36 -> 0 | J7: =Projectbegroting!D36 -> 56 | K7: =Projectbegroting!E36 -> 0
A8: =CONCATENATE(D8,H8) -> 30626-0003MS | C8: =Projectbegroting!$B$8 -> Klant in zicht 2027 | D8: =Projectbegroting!$B$9 -> 30626-0003 | H8: MS | I8: =Projectbegroting!F37 -> 0 | J8: =Projectbegroting!D37 -> 50 | K8: =Projectbegroting!E37 -> 0
A9: =CONCATENATE(D9,H9) -> 30626-0003PDO | C9: =Projectbegroting!$B$8 -> Klant in zicht 2027 | D9: =Projectbegroting!$B$9 -> 30626-0003 | H9: PDO | I9: =Projectbegroting!F38 -> 0 | J9: =Projectbegroting!D38 -> 87 | K9: =Projectbegroting!E38 -> 0
A10: =CONCATENATE(D10,H10) -> 30626-0003PRO | C10: =Projectbegroting!$B$8 -> Klant in zicht 2027 | D10: =Projectbegroting!$B$9 -> 30626-0003 | H10: PRO | I10: =Projectbegroting!F39 -> 0 | J10: =Projectbegroting!D39 -> 56 | K10: =Projectbegroting!E39 -> 0
A11: =CONCATENATE(D11,H11) -> 30626-0003PS | C11: =Projectbegroting!$B$8 -> Klant in zicht 2027 | D11: =Projectbegroting!$B$9 -> 30626-0003 | H11: PS | I11: =Projectbegroting!F40 -> 0 | J11: =Projectbegroting!D40 -> 46 | K11: =Projectbegroting!E40 -> 0
A12: =CONCATENATE(D12,H12) -> 30626-0003TOE | C12: =Projectbegroting!$B$8 -> Klant in zicht 2027 | D12: =Projectbegroting!$B$9 -> 30626-0003 | H12: TOE | I12: =Projectbegroting!F41 -> 0 | J12: =Projectbegroting!D41 -> 63 | K12: =Projectbegroting!E41 -> 0
A13: =CONCATENATE(D13,H13) -> 30626-0003TOM | C13: =Projectbegroting!$B$8 -> Klant in zicht 2027 | D13: =Projectbegroting!$B$9 -> 30626-0003 | H13: TOM | I13: =Projectbegroting!F42 -> 0 | J13: =Projectbegroting!D42 -> 50 | K13: =Projectbegroting!E42 -> 0
... A67: =CONCATENATE(D67,H67) -> 30626-0003730 | C67: =Projectbegroting!$B$8 -> Klant in zicht 2027 | D67: =Projectbegroting!$B$9 -> 30626-0003 | H67: 730 | I67: =Projectbegroting!F96 -> 0 | J67: =Projectbegroting!D96 -> 0.05 | K67: =Projectbegroting!E96 -> 0
A68: =CONCATENATE(D68,H68) -> 30626-0003740 | B68: =""&Projectbegroting!F65 | C68: =Projectbegroting!$B$8 -> Klant in zicht 2027 | D68: =Projectbegroting!$B$9 -> 30626-0003 | H68: 740 | I68: =Projectbegroting!F97 -> 1 | J68: =Projectbegroting!D97 -> 0 | K68: =Projectbegroting!E97 -> 0
A69: =CONCATENATE(D69,H69) -> 30626-0003843 | C69: =Projectbegroting!$B$8 -> Klant in zicht 2027 | D69: =Projectbegroting!$B$9 -> 30626-0003 | H69: 843 | I69: =Projectbegroting!F98 -> 1 | J69: =Projectbegroting!D98 -> 0 | K69: =Projectbegroting!E98 -> 0

Sheet Probuto
A1: Rekening | B1: Kostenplaats | C1: Kostendrager | D1: variant | E1: jan | F1: feb | G1: maart | H1: april | I1: mei | J1: juni | K1: juli | L1: aug | M1: sep | N1: okt | O1: nov | P1: dec
A2: 8320 | B2: =IF(Projectbegroting!$B$18=Lijsten!$T$2,Projectbegroting!$B$19,"") | C2: =IF(Projectbegroting!$B$18=Lijsten!$T$2,Projectbegroting!$B$20,"") | D2: =IF(Projectbegroting!$B$18=Lijsten!$T$2,Projectbegroting!$B$21,"") | E2: =IFERROR(-IF(OR(Projectbegroting!$B$18=Lijsten!$T$2,Projectbegroting!$B$18=Lijsten!$W$2),SUMIF(Projectbegroting!$A:$A,"omzet",Projectbegroting!G:G),""),"") | F2: =IFERROR(-IF(OR(Projectbegroting!$B$18=Lijsten!$T$2,Projectbegroting!$B$18=Lijsten!$W$2),SUMIF(Projectbegroting!$A:$A,"omzet",Projectbegroting!H:H),""),"") | G2: =IFERROR(-IF(OR(Projectbegroting!$B$18=Lijsten!$T$2,Projectbegroting!$B$18=Lijsten!$W$2),SUMIF(Projectbegroting!$A:$A,"omzet",Projectbegroting!I:I),""),"") | H2: =IFERROR(-IF(OR(Projectbegroting!$B$18=Lijsten!$T$2,Projectbegroting!$B$18=Lijsten!$W$2),SUMIF(Projectbegroting!$A:$A,"omzet",Projectbegroting!J:J),""),"") | I2: =IFERROR(-IF(OR(Projectbegroting!$B$18=Lijsten!$T$2,Projectbegroting!$B$18=Lijsten!$W$2),SUMIF(Projectbegroting!$A:$A,"omzet",Projectbegroting!K:K),""),"") | J2: =IFERROR(-IF(OR(Projectbegroting!$B$18=Lijsten!$T$2,Projectbegroting!$B$18=Lijsten!$W$2),SUMIF(Projectbegroting!$A:$A,"omzet",Projectbegroting!L:L),""),"") | K2: =IFERROR(-IF(OR(Projectbegroting!$B$18=Lijsten!$T$2,Projectbegroting!$B$18=Lijsten!$W$2),SUMIF(Projectbegroting!$A:$A,"omzet",Projectbegroting!M:M),""),"") | L2: =IFERROR(-IF(OR(Projectbegroting!$B$18=Lijsten!$T$2,Projectbegroting!$B$18=Lijsten!$W$2),SUMIF(Projectbegroting!$A:$A,"omzet",Projectbegroting!N:N),""),"") | M2: =IFERROR(-IF(OR(Projectbegroting!$B$18=Lijsten!$T$2,Projectbegroting!$B$18=Lijsten!$W$2),SUMIF(Projectbegroting!$A:$A,"omzet",Projectbegroting!O:O),""),"") | N2: =IFERROR(-IF(OR(Projectbegroting!$B$18=Lijsten!$T$2,Projectbegroting!$B$18=Lijsten!$W$2),SUMIF(Projectbegroting!$A:$A,"omzet",Projectbegroting!P:P),""),"") | O2: =IFERROR(-IF(OR(Projectbegroting!$B$18=Lijsten!$T$2,Projectbegroting!$B$18=Lijsten!$W$2),SUMIF(Projectbegroting!$A:$A,"omzet",Projectbegroting!Q:Q),""),"") | P2: =IFERROR(-IF(OR(Projectbegroting!$B$18=Lijsten!$T$2,Projectbegroting!$B$18=Lijsten!$W$2),SUMIF(Projectbegroting!$A:$A,"omzet",Projectbegroting!R:R),""),"")
A3: 4700 | B3: =IF(Projectbegroting!$B$18=Lijsten!$T$2,Projectbegroting!$B$19,"") | C3: =IF(Projectbegroting!$B$18=Lijsten!$T$2,Projectbegroting!$B$20,"") | D3: =IF(Projectbegroting!$B$18=Lijsten!$T$2,Projectbegroting!$B$21,"") | E3: =IF(Projectbegroting!$B$18=Lijsten!$T$2,SUMIF(Projectbegroting!$A:$A,"Onkosten",Projectbegroting!G:G),"") | F3: =IF(Projectbegroting!$B$18=Lijsten!$T$2,SUMIF(Projectbegroting!$A:$A,"Onkosten",Projectbegroting!H:H),"") | G3: =IF(Projectbegroting!$B$18=Lijsten!$T$2,SUMIF(Projectbegroting!$A:$A,"Onkosten",Projectbegroting!I:I),"") | H3: =IF(Projectbegroting!$B$18=Lijsten!$T$2,SUMIF(Projectbegroting!$A:$A,"Onkosten",Projectbegroting!J:J),"") | I3: =IF(Projectbegroting!$B$18=Lijsten!$T$2,SUMIF(Projectbegroting!$A:$A,"Onkosten",Projectbegroting!K:K),"") | J3: =IF(Projectbegroting!$B$18=Lijsten!$T$2,SUMIF(Projectbegroting!$A:$A,"Onkosten",Projectbegroting!L:L),"") | K3: =IF(Projectbegroting!$B$18=Lijsten!$T$2,SUMIF(Projectbegroting!$A:$A,"Onkosten",Projectbegroting!M:M),"") | L3: =IF(Projectbegroting!$B$18=Lijsten!$T$2,SUMIF(Projectbegroting!$A:$A,"Onkosten",Projectbegroting!N:N),"") | M3: =IF(Projectbegroting!$B$18=Lijsten!$T$2,SUMIF(Projectbegroting!$A:$A,"Onkosten",Projectbegroting!O:O),"") | N3: =IF(Projectbegroting!$B$18=Lijsten!$T$2,SUMIF(Projectbegroting!$A:$A,"Onkosten",Projectbegroting!P:P),"") | O3: =IF(Projectbegroting!$B$18=Lijsten!$T$2,SUMIF(Projectbegroting!$A:$A,"Onkosten",Projectbegroting!Q:Q),"") | P3: =IF(Projectbegroting!$B$18=Lijsten!$T$2,SUMIF(Projectbegroting!$A:$A,"Onkosten",Projectbegroting!R:R),"")
A4: 4703 | B4: =IF(Projectbegroting!$B$18=Lijsten!$W$2,Projectbegroting!$B$19,"") -> 7040 | C4: =IF(Projectbegroting!$B$18=Lijsten!$W$2,Projectbegroting!$B$20,"") -> 0 | D4: =IF(Projectbegroting!$B$18=Lijsten!$W$2,Projectbegroting!$B$21,"") -> 0 | E4: =IF(Projectbegroting!$B$18=Lijsten!$W$2,SUMIF(Projectbegroting!$A:$A,"Onkosten",Projectbegroting!G:G)+SUMIF(Projectbegroting!$A:$A,"Inleen medewerkers",Projectbegroting!G:G),"") -> 0 | F4: =IF(Projectbegroting!$B$18=Lijsten!$W$2,SUMIF(Projectbegroting!$A:$A,"Onkosten",Projectbegroting!H:H)+SUMIF(Projectbegroting!$A:$A,"Inleen medewerkers",Projectbegroting!H:H),"") -> 0 | G4: =IF(Projectbegroting!$B$18=Lijsten!$W$2,SUMIF(Projectbegroting!$A:$A,"Onkosten",Projectbegroting!I:I)+SUMIF(Projectbegroting!$A:$A,"Inleen medewerkers",Projectbegroting!I:I),"") -> 0 | H4: =IF(Projectbegroting!$B$18=Lijsten!$W$2,SUMIF(Projectbegroting!$A:$A,"Onkosten",Projectbegroting!J:J)+SUMIF(Projectbegroting!$A:$A,"Inleen medewerkers",Projectbegroting!J:J),"") -> 0 | I4: =IF(Projectbegroting!$B$18=Lijsten!$W$2,SUMIF(Projectbegroting!$A:$A,"Onkosten",Projectbegroting!K:K)+SUMIF(Projectbegroting!$A:$A,"Inleen medewerkers",Projectbegroting!K:K),"") -> 0 | J4: =IF(Projectbegroting!$B$18=Lijsten!$W$2,SUMIF(Projectbegroting!$A:$A,"Onkosten",Projectbegroting!L:L)+SUMIF(Projectbegroting!$A:$A,"Inleen medewerkers",Projectbegroting!L:L),"") -> 0 | K4: =IF(Projectbegroting!$B$18=Lijsten!$W$2,SUMIF(Projectbegroting!$A:$A,"Onkosten",Projectbegroting!M:M)+SUMIF(Projectbegroting!$A:$A,"Inleen medewerkers",Projectbegroting!M:M),"") -> 0 | L4: =IF(Projectbegroting!$B$18=Lijsten!$W$2,SUMIF(Projectbegroting!$A:$A,"Onkosten",Projectbegroting!N:N)+SUMIF(Projectbegroting!$A:$A,"Inleen medewerkers",Projectbegroting!N:N),"") -> 0 | M4: =IF(Projectbegroting!$B$18=Lijsten!$W$2,SUMIF(Projectbegroting!$A:$A,"Onkosten",Projectbegroting!O:O)+SUMIF(Projectbegroting!$A:$A,"Inleen medewerkers",Projectbegroting!O:O),"") -> 0 | N4: =IF(Projectbegroting!$B$18=Lijsten!$W$2,SUMIF(Projectbegroting!$A:$A,"Onkosten",Projectbegroting!P:P)+SUMIF(Projectbegroting!$A:$A,"Inleen medewerkers",Projectbegroting!P:P),"") -> 0 | O4: =IF(Projectbegroting!$B$18=Lijsten!$W$2,SUMIF(Projectbegroting!$A:$A,"Onkosten",Projectbegroting!Q:Q)+SUMIF(Projectbegroting!$A:$A,"Inleen medewerkers",Projectbegroting!Q:Q),"") -> 0 | P4: =IF(Projectbegroting!$B$18=Lijsten!$W$2,SUMIF(Projectbegroting!$A:$A,"Onkosten",Projectbegroting!R:R)+SUMIF(Projectbegroting!$A:$A,"Inleen medewerkers",Projectbegroting!R:R),"") -> 0
A5: 4705 | B5: =IF(OR(Projectbegroting!$B$18=Lijsten!$T$2),Projectbegroting!B19,"") | C5: =IF(OR(Projectbegroting!$B$18=Lijsten!$T$2),Projectbegroting!B20,"") | D5: =IF(OR(Projectbegroting!$B$18=Lijsten!$T$2),Projectbegroting!B21,"") | E5: =IFERROR(IF(OR(Projectbegroting!$B$18=Lijsten!$T$2),SUMIF(Projectbegroting!$A:$A,"Inleen medewerkers",Projectbegroting!G:G),""),"") | F5: =IFERROR(IF(OR(Projectbegroting!$B$18=Lijsten!$T$2),SUMIF(Projectbegroting!$A:$A,"Inleen medewerkers",Projectbegroting!H:H),""),"") | G5: =IFERROR(IF(OR(Projectbegroting!$B$18=Lijsten!$T$2),SUMIF(Projectbegroting!$A:$A,"Inleen medewerkers",Projectbegroting!I:I),""),"") | H5: =IFERROR(IF(OR(Projectbegroting!$B$18=Lijsten!$T$2),SUMIF(Projectbegroting!$A:$A,"Inleen medewerkers",Projectbegroting!J:J),""),"") | I5: =IFERROR(IF(OR(Projectbegroting!$B$18=Lijsten!$T$2),SUMIF(Projectbegroting!$A:$A,"Inleen medewerkers",Projectbegroting!K:K),""),"") | J5: =IFERROR(IF(OR(Projectbegroting!$B$18=Lijsten!$T$2),SUMIF(Projectbegroting!$A:$A,"Inleen medewerkers",Projectbegroting!L:L),""),"") | K5: =IFERROR(IF(OR(Projectbegroting!$B$18=Lijsten!$T$2),SUMIF(Projectbegroting!$A:$A,"Inleen medewerkers",Projectbegroting!M:M),""),"") | L5: =IFERROR(IF(OR(Projectbegroting!$B$18=Lijsten!$T$2),SUMIF(Projectbegroting!$A:$A,"Inleen medewerkers",Projectbegroting!N:N),""),"") | M5: =IFERROR(IF(OR(Projectbegroting!$B$18=Lijsten!$T$2),SUMIF(Projectbegroting!$A:$A,"Inleen medewerkers",Projectbegroting!O:O),""),"") | N5: =IFERROR(IF(OR(Projectbegroting!$B$18=Lijsten!$T$2),SUMIF(Projectbegroting!$A:$A,"Inleen medewerkers",Projectbegroting!P:P),""),"") | O5: =IFERROR(IF(OR(Projectbegroting!$B$18=Lijsten!$T$2),SUMIF(Projectbegroting!$A:$A,"Inleen medewerkers",Projectbegroting!Q:Q),""),"") | P5: =IFERROR(IF(OR(Projectbegroting!$B$18=Lijsten!$T$2),SUMIF(Projectbegroting!$A:$A,"Inleen medewerkers",Projectbegroting!R:R),""),"")
A6: 4710 | B6: =IF(Projectbegroting!$B$18=Lijsten!$Z$2,Projectbegroting!$B$19,"") | C6: =IF(Projectbegroting!$B$18=Lijsten!$Z$2,Projectbegroting!$B$20,"") | D6: =IF(Projectbegroting!$B$18=Lijsten!$Z$2,Projectbegroting!$B$21,"") | E6: =IF(Projectbegroting!$B$18=Lijsten!$Z$2,SUMIF(Projectbegroting!$A:$A,"Onkosten",Projectbegroting!G:G)+SUMIF(Projectbegroting!$A:$A,"Inleen medewerkers",Projectbegroting!G:G),"") | F6: =IF(Projectbegroting!$B$18=Lijsten!$Z$2,SUMIF(Projectbegroting!$A:$A,"Onkosten",Projectbegroting!H:H)+SUMIF(Projectbegroting!$A:$A,"Inleen medewerkers",Projectbegroting!H:H),"") | G6: =IF(Projectbegroting!$B$18=Lijsten!$Z$2,SUMIF(Projectbegroting!$A:$A,"Onkosten",Projectbegroting!I:I)+SUMIF(Projectbegroting!$A:$A,"Inleen medewerkers",Projectbegroting!I:I),"") | H6: =IF(Projectbegroting!$B$18=Lijsten!$Z$2,SUMIF(Projectbegroting!$A:$A,"Onkosten",Projectbegroting!J:J)+SUMIF(Projectbegroting!$A:$A,"Inleen medewerkers",Projectbegroting!J:J),"") | I6: =IF(Projectbegroting!$B$18=Lijsten!$Z$2,SUMIF(Projectbegroting!$A:$A,"Onkosten",Projectbegroting!K:K)+SUMIF(Projectbegroting!$A:$A,"Inleen medewerkers",Projectbegroting!K:K),"") | J6: =IF(Projectbegroting!$B$18=Lijsten!$Z$2,SUMIF(Projectbegroting!$A:$A,"Onkosten",Projectbegroting!L:L)+SUMIF(Projectbegroting!$A:$A,"Inleen medewerkers",Projectbegroting!L:L),"") | K6: =IF(Projectbegroting!$B$18=Lijsten!$Z$2,SUMIF(Projectbegroting!$A:$A,"Onkosten",Projectbegroting!M:M)+SUMIF(Projectbegroting!$A:$A,"Inleen medewerkers",Projectbegroting!M:M),"") | L6: =IF(Projectbegroting!$B$18=Lijsten!$Z$2,SUMIF(Projectbegroting!$A:$A,"Onkosten",Projectbegroting!N:N)+SUMIF(Projectbegroting!$A:$A,"Inleen medewerkers",Projectbegroting!N:N),"") | M6: =IF(Projectbegroting!$B$18=Lijsten!$Z$2,SUMIF(Projectbegroting!$A:$A,"Onkosten",Projectbegroting!O:O)+SUMIF(Projectbegroting!$A:$A,"Inleen medewerkers",Projectbegroting!O:O),"") | N6: =IF(Projectbegroting!$B$18=Lijsten!$Z$2,SUMIF(Projectbegroting!$A:$A,"Onkosten",Projectbegroting!P:P)+SUMIF(Projectbegroting!$A:$A,"Inleen medewerkers",Projectbegroting!P:P),"") | O6: =IF(Projectbegroting!$B$18=Lijsten!$Z$2,SUMIF(Projectbegroting!$A:$A,"Onkosten",Projectbegroting!Q:Q)+SUMIF(Projectbegroting!$A:$A,"Inleen medewerkers",Projectbegroting!Q:Q),"") | P6: =IF(Projectbegroting!$B$18=Lijsten!$Z$2,SUMIF(Projectbegroting!$A:$A,"Onkosten",Projectbegroting!R:R)+SUMIF(Projectbegroting!$A:$A,"Inleen medewerkers",Projectbegroting!R:R),"")
A7: 5500 | B7: =IF(OR(Projectbegroting!B18=Lijsten!T2,Projectbegroting!B18=Lijsten!W2),Projectbegroting!B19,"") -> 7040 | C7: =IF(OR(Projectbegroting!B18=Lijsten!T2,Projectbegroting!B18=Lijsten!W2),Projectbegroting!B20,"") -> 0 | D7: =IF(OR(Projectbegroting!B18=Lijsten!T2,Projectbegroting!B18=Lijsten!W2),Projectbegroting!B21,"") -> 0 | E7: =IF(OR(Projectbegroting!$B$18=Lijsten!$T$2,Projectbegroting!$B$18=Lijsten!$W$2),SUMIF(Projectbegroting!$A:$A,"Eigen medewerkers",Projectbegroting!G:G),"") -> 0 | F7: =IF(OR(Projectbegroting!$B$18=Lijsten!$T$2,Projectbegroting!$B$18=Lijsten!$W$2),SUMIF(Projectbegroting!$A:$A,"Eigen medewerkers",Projectbegroting!H:H),"") -> 0 | G7: =IF(OR(Projectbegroting!$B$18=Lijsten!$T$2,Projectbegroting!$B$18=Lijsten!$W$2),SUMIF(Projectbegroting!$A:$A,"Eigen medewerkers",Projectbegroting!I:I),"") -> 0 | H7: =IF(OR(Projectbegroting!$B$18=Lijsten!$T$2,Projectbegroting!$B$18=Lijsten!$W$2),SUMIF(Projectbegroting!$A:$A,"Eigen medewerkers",Projectbegroting!J:J),"") -> 0 | I7: =IF(OR(Projectbegroting!$B$18=Lijsten!$T$2,Projectbegroting!$B$18=Lijsten!$W$2),SUMIF(Projectbegroting!$A:$A,"Eigen medewerkers",Projectbegroting!K:K),"") -> 0 | J7: =IF(OR(Projectbegroting!$B$18=Lijsten!$T$2,Projectbegroting!$B$18=Lijsten!$W$2),SUMIF(Projectbegroting!$A:$A,"Eigen medewerkers",Projectbegroting!L:L),"") -> 0 | K7: =IF(OR(Projectbegroting!$B$18=Lijsten!$T$2,Projectbegroting!$B$18=Lijsten!$W$2),SUMIF(Projectbegroting!$A:$A,"Eigen medewerkers",Projectbegroting!M:M),"") -> 0 | L7: =IF(OR(Projectbegroting!$B$18=Lijsten!$T$2,Projectbegroting!$B$18=Lijsten!$W$2),SUMIF(Projectbegroting!$A:$A,"Eigen medewerkers",Projectbegroting!N:N),"") -> 0 | M7: =IF(OR(Projectbegroting!$B$18=Lijsten!$T$2,Projectbegroting!$B$18=Lijsten!$W$2),SUMIF(Projectbegroting!$A:$A,"Eigen medewerkers",Projectbegroting!O:O),"") -> 0 | N7: =IF(OR(Projectbegroting!$B$18=Lijsten!$T$2,Projectbegroting!$B$18=Lijsten!$W$2),SUMIF(Projectbegroting!$A:$A,"Eigen medewerkers",Projectbegroting!P:P),"") -> 0 | O7: =IF(OR(Projectbegroting!$B$18=Lijsten!$T$2,Projectbegroting!$B$18=Lijsten!$W$2),SUMIF(Projectbegroting!$A:$A,"Eigen medewerkers",Projectbegroting!Q:Q),"") -> 0 | P7: =IF(OR(Projectbegroting!$B$18=Lijsten!$T$2,Projectbegroting!$B$18=Lijsten!$W$2),SUMIF(Projectbegroting!$A:$A,"Eigen medewerkers",Projectbegroting!R:R),"") -> 0
A8: 5501 | B8: =IF(Projectbegroting!$B$18=Lijsten!$Z$2,Projectbegroting!$B$19,"") | C8: =IF(Projectbegroting!$B$18=Lijsten!$Z$2,Projectbegroting!$B$20,"") | D8: =IF(Projectbegroting!$B$18=Lijsten!$Z$2,Projectbegroting!$B$21,"") | E8: =IF(Projectbegroting!$B$18=Lijsten!$Z$2,SUMIF(Projectbegroting!$A:$A,"Eigen medewerkers",Projectbegroting!G:G),"") | F8: =IF(Projectbegroting!$B$18=Lijsten!$Z$2,SUMIF(Projectbegroting!$A:$A,"Eigen medewerkers",Projectbegroting!H:H),"") | G8: =IF(Projectbegroting!$B$18=Lijsten!$Z$2,SUMIF(Projectbegroting!$A:$A,"Eigen medewerkers",Projectbegroting!I:I),"") | H8: =IF(Projectbegroting!$B$18=Lijsten!$Z$2,SUMIF(Projectbegroting!$A:$A,"Eigen medewerkers",Projectbegroting!J:J),"") | I8: =IF(Projectbegroting!$B$18=Lijsten!$Z$2,SUMIF(Projectbegroting!$A:$A,"Eigen medewerkers",Projectbegroting!K:K),"") | J8: =IF(Projectbegroting!$B$18=Lijsten!$Z$2,SUMIF(Projectbegroting!$A:$A,"Eigen medewerkers",Projectbegroting!L:L),"") | K8: =IF(Projectbegroting!$B$18=Lijsten!$Z$2,SUMIF(Projectbegroting!$A:$A,"Eigen medewerkers",Projectbegroting!M:M),"") | L8: =IF(Projectbegroting!$B$18=Lijsten!$Z$2,SUMIF(Projectbegroting!$A:$A,"Eigen medewerkers",Projectbegroting!N:N),"") | M8: =IF(Projectbegroting!$B$18=Lijsten!$Z$2,SUMIF(Projectbegroting!$A:$A,"Eigen medewerkers",Projectbegroting!O:O),"") | N8: =IF(Projectbegroting!$B$18=Lijsten!$Z$2,SUMIF(Projectbegroting!$A:$A,"Eigen medewerkers",Projectbegroting!P:P),"") | O8: =IF(Projectbegroting!$B$18=Lijsten!$Z$2,SUMIF(Projectbegroting!$A:$A,"Eigen medewerkers",Projectbegroting!Q:Q),"") | P8: =IF(Projectbegroting!$B$18=Lijsten!$Z$2,SUMIF(Projectbegroting!$A:$A,"Eigen medewerkers",Projectbegroting!R:R),"")
A9: 5600 | B9: =B7 -> 7040 | E9: =IFERROR(-E7,"") -> 0 | F9: =IFERROR(-F7,"") -> 0 | G9: =IFERROR(-G7,"") -> 0 | H9: =IFERROR(-H7,"") -> 0 | I9: =IFERROR(-I7,"") -> 0 | J9: =IFERROR(-J7,"") -> 0 | K9: =IFERROR(-K7,"") -> 0 | L9: =IFERROR(-L7,"") -> 0 | ... P9: =IFERROR(-P7,"") -> 0
A10: 5601 | B10: =B8 | E10: =IFERROR(-E8,"") | F10: =IFERROR(-F8,"") | G10: =IFERROR(-G8,"") | H10: =IFERROR(-H8,"") | I10: =IFERROR(-I8,"") | J10: =IFERROR(-J8,"") | K10: =IFERROR(-K8,"") | L10: =IFERROR(-L8,"") | ... P10: =IFERROR(-P8,"")
B11: =B8 | E11: =IFERROR(-E8,"") | F11: =IFERROR(-F8,"") | G11: =IFERROR(-G8,"") | H11: =IFERROR(-H8,"") | I11: =IFERROR(-I8,"") | J11: =IFERROR(-J8,"") | K11: =IFERROR(-K8,"") | L11: =IFERROR(-L8,"") | ... P11: =IFERROR(-P8,"")

Sheet Lijsten
A2: Projectgroep | C2: Kostenplaats | E2: Kostendrager | G2: Variant | I2: BTW-Code | K2: Controller | N2: Projectleider | Q2: Opdrachtgever | T2: OiOvD | W2: Kosten | Z2: Invest
A3: Invest - Investeringsprojecten | C3: 5110 - Uitgeverij PO Belast | I3: EU-B; export binnen eu belast | K3: Elise Borgers | L3: 42805 | N3: Anja de Wijs | O3: 1180 | Q3: Alma van Til | R3: 1160 | T3: Eigen medewerkers | U3: 5500 | W3: Eigen medewerkers | X3: 5500 | Z3: Eigen medewerkers | AA3: 5501
A4: Kosten - Beheeractiviteiten | C4: 5111 - Uitgeverij PO Vrijgesteld | E4: KIB | G4: DUI | I4: EX-B ; export buiten eu belast | K4: Steef Berkeljon | L4: 43515 | N4: Anne Hettema | O4: 24745 | Q4: Frans van Dijk | R4: 30425 | T4: Inleen medewerkers | U4: 4705 | W4: Inleen medewerkers | X4: 4703 | Z4: Inleen medewerkers | AA4: 4710
A5: OiOvD - Ontwikkeling in opdracht van derden | C5: 5120 - Uitgeverij VO Belast | E5: LIBDST | G5: ENG | I5: EX-V ; export buiten ex vrijgesteld | K5: George Pavel | L5: 2061 | N5: Antoinette van het Hul - Derksen | O5: 3097 | Q5: Jasper Kwakkelstein | R5: 2950 | T5: Onkosten | U5: 4700 | W5: Onkosten | X5: 4703 | Z5: Onkosten | AA5: 4710
C6: 5121 - Uitgeverij VO Vrijgesteld | E6: LIBLVS | G6: FRA | I6: NL-B ; btw belast hoog | K6: Tim Visser | L6: 29845 | N6: Asther den Boogert | O6: 2718 | Q6: Joanne van Emmerik | R6: 2815 | T6: Omzet | U6: 8320 | W6: Omzet | X6: 8320 | Z6: Omzet | AA6: 8320
C7: 5310 - Professionals Belast | E7: TRAINCERTPO | G7: NED | I7: NL-P ; btw belast hoog prorata | N7: Frans van Dijk | O7: 30425 | Q7: Marc van der Lee | R7: 9005
C8: 5311 - Professionals Vrijgesteld | E8: CVVO | G8: SPA | I8: NL-V ; btw vrijgesteld | N8: Hanneke Bouwmans - de Jong | O8: 2131 | Q8: Rianne Hommelberg | R8: 24255
C9: 5520 - Proces support | E9: KLT | G9: PABOPAR | N9: Jasper de Vries | O9: 34495 | Q9: Aufa Ramdani | R9: 21825
C10: 5530 - Media support | E10: TRAINCERTVO | G10: PABOVH | N10: Jasper Kwakkelstein | O10: 2950 | Q10: Saila Kiriwenno - Dovermann | R10: 35055
C11: 5570 - Trainers | E11: BONDERW | G11: TRAINCERT | N11: Jill Linders | O11: 24105 | Q11: Manon Heesen | R11: 3390
C12: 5621 - Buitendienst POVO | E12: ONDERZOEK | G12: PEIL | N12: Joanne van Emmerik | O12: 2815 | Q12: Jan Spruijt | R12: 35505
C13: 5622 - Binnendienst POVO | E13: TALEN | G13: INBU | N13: Jossie Hunting | O13: 30775 | Q13: Dennis van den Broek | R13: 2712
C14: 5630 - Klantenservice | E14: ZM | G14: STEX | N14: Kathelijn Zwols | O14: 11895 | Q14: Marijn Krijgsman | R14: 34955
C15: 5720 - Staf | G15: NATURALISATIE | N15: Loes van den Heuvel | O15: 13495 | Q15: Judith Vloedgraven | R15: 2522
C16: 6010 - Data & Tech | G16: BODEM | N16: Manon Heesen | O16: 3390 | Q16: Bert Thijs de Jong | R16: 34815
C17: 7020 - Overhead Onbelast | G17: CDD | N17: Onne Smeets | O17: 36625 | Q17: Cornelis Richter | R17: 41265
C18: 7040 - Overhead Belast | G18: ISSOEPA | N18: Nienke Elijzen | O18: 31935 | Q18: Jorine Vermeulen | R18: 24945
C19: 9545 - IVIT BV (BTW vrij) | G19: ISSOLPA | N19: Peter van der Leek | O19: 32085 | Q19: Leontine Derks | R19: 36555
C20: 9546 - IVIT BV (belast) | G20: LASSER | N20: Rianne Hommelberg | O20: 24255 | Q20: Manon Heesen | R20: 3390
G21: MEDREK | N21: Rick te Kloeze | O21: 2926 | Q21: Rick Godschalk | R21: 2931
G22: NBA | N22: Rozanne Drexler | O22: 3064 | Q22: Esther Scolten | R22: 41725
G23: NCTV | N23: Sanne Lecluijze | O23: 2666
G24: VAKMANROUTE | N24: Meike Hennekam | O24: 29935
N25: Saila Kiriwenno - Dovermann | O25: 35055
N26: Inge Mulder | O26: 40975
N27: Charlotte van der Meer | O27: 36745
N28: Jama Sarwar | O28: 43035
N29: Jorine Vermeulen | O29: 24945
N30: Josine Verhagen | O30: 35335
N31: Pim de Burger | O31: 25955

Sheet report B_CategorieBoekjaar
A1: BedrijfsCode | B1: Boekjaar | C1: CategorieCode | D1: CategorieNaam | E1: CategorieGroep | F1: PrijsInkoop | G1: PrijsVerkoop | H1: hulpkolom kostprijs | I1: Hulp kolom verkoopprijs
A2: 001 | B2: 46023 | C2: 310 | D2: Zaalhuur en Catering (extern) | E2: Kosten | F2: 0 | G2: 0 | H2: =IF(report_B_CategorieBoekjaar[[#This Row],[BedrijfsCode]]="002",IF(report_B_CategorieBoekjaar[[#This Row],[Boekjaar]]=Projectbegroting!$K$1,report_B_CategorieBoekjaar[[#This Row],[CategorieCode]],0),0) -> 0 | I2: =IF(report_B_CategorieBoekjaar[[#This Row],[BedrijfsCode]]="001",IF(report_B_CategorieBoekjaar[[#This Row],[Boekjaar]]=Projectbegroting!$K$1,report_B_CategorieBoekjaar[[#This Row],[CategorieCode]],0),0) -> 310
A3: 001 | B3: 46023 | C3: 350 | D3: ICT hardware en software | E3: Kosten | F3: 0 | G3: 0 | H3: =IF(report_B_CategorieBoekjaar[[#This Row],[BedrijfsCode]]="002",IF(report_B_CategorieBoekjaar[[#This Row],[Boekjaar]]=Projectbegroting!$K$1,report_B_CategorieBoekjaar[[#This Row],[CategorieCode]],0),0) -> 0 | I3: =IF(report_B_CategorieBoekjaar[[#This Row],[BedrijfsCode]]="001",IF(report_B_CategorieBoekjaar[[#This Row],[Boekjaar]]=Projectbegroting!$K$1,report_B_CategorieBoekjaar[[#This Row],[CategorieCode]],0),0) -> 350
A4: 001 | B4: 46023 | C4: 410 | D4: Advies en Consultant | E4: Kosten | F4: 0 | G4: 0 | H4: =IF(report_B_CategorieBoekjaar[[#This Row],[BedrijfsCode]]="002",IF(report_B_CategorieBoekjaar[[#This Row],[Boekjaar]]=Projectbegroting!$K$1,report_B_CategorieBoekjaar[[#This Row],[CategorieCode]],0),0) -> 0 | I4: =IF(report_B_CategorieBoekjaar[[#This Row],[BedrijfsCode]]="001",IF(report_B_CategorieBoekjaar[[#This Row],[Boekjaar]]=Projectbegroting!$K$1,report_B_CategorieBoekjaar[[#This Row],[CategorieCode]],0),0) -> 410
A5: 001 | B5: 46023 | C5: 470 | D5: Internet en Telecommunicatie | E5: Kosten | F5: 0 | G5: 0 | H5: =IF(report_B_CategorieBoekjaar[[#This Row],[BedrijfsCode]]="002",IF(report_B_CategorieBoekjaar[[#This Row],[Boekjaar]]=Projectbegroting!$K$1,report_B_CategorieBoekjaar[[#This Row],[CategorieCode]],0),0) -> 0 | I5: =IF(report_B_CategorieBoekjaar[[#This Row],[BedrijfsCode]]="001",IF(report_B_CategorieBoekjaar[[#This Row],[Boekjaar]]=Projectbegroting!$K$1,report_B_CategorieBoekjaar[[#This Row],[CategorieCode]],0),0) -> 470
A6: 001 | B6: 46023 | C6: 490 | D6: Kantoorbenodigdheden | E6: Kosten | F6: 0 | G6: 0 | H6: =IF(report_B_CategorieBoekjaar[[#This Row],[BedrijfsCode]]="002",IF(report_B_CategorieBoekjaar[[#This Row],[Boekjaar]]=Projectbegroting!$K$1,report_B_CategorieBoekjaar[[#This Row],[CategorieCode]],0),0) -> 0 | I6: =IF(report_B_CategorieBoekjaar[[#This Row],[BedrijfsCode]]="001",IF(report_B_CategorieBoekjaar[[#This Row],[Boekjaar]]=Projectbegroting!$K$1,report_B_CategorieBoekjaar[[#This Row],[CategorieCode]],0),0) -> 490
A7: 001 | B7: 46023 | C7: 491 | D7: Lidmaatschappen, inschrijvingen en documentatie abonnementen | E7: Kosten | F7: 0 | G7: 0 | H7: =IF(report_B_CategorieBoekjaar[[#This Row],[BedrijfsCode]]="002",IF(report_B_CategorieBoekjaar[[#This Row],[Boekjaar]]=Projectbegroting!$K$1,report_B_CategorieBoekjaar[[#This Row],[CategorieCode]],0),0) -> 0 | I7: =IF(report_B_CategorieBoekjaar[[#This Row],[BedrijfsCode]]="001",IF(report_B_CategorieBoekjaar[[#This Row],[Boekjaar]]=Projectbegroting!$K$1,report_B_CategorieBoekjaar[[#This Row],[CategorieCode]],0),0) -> 491
A8: 001 | B8: 46023 | C8: 510 | D8: Verzendkosten | E8: Kosten | F8: 0 | G8: 0 | H8: =IF(report_B_CategorieBoekjaar[[#This Row],[BedrijfsCode]]="002",IF(report_B_CategorieBoekjaar[[#This Row],[Boekjaar]]=Projectbegroting!$K$1,report_B_CategorieBoekjaar[[#This Row],[CategorieCode]],0),0) -> 0 | I8: =IF(report_B_CategorieBoekjaar[[#This Row],[BedrijfsCode]]="001",IF(report_B_CategorieBoekjaar[[#This Row],[Boekjaar]]=Projectbegroting!$K$1,report_B_CategorieBoekjaar[[#This Row],[CategorieCode]],0),0) -> 510
A9: 001 | B9: 46023 | C9: 520 | D9: Drukwerk en verpakkingen | E9: Kosten | F9: 0 | G9: 0 | H9: =IF(report_B_CategorieBoekjaar[[#This Row],[BedrijfsCode]]="002",IF(report_B_CategorieBoekjaar[[#This Row],[Boekjaar]]=Projectbegroting!$K$1,report_B_CategorieBoekjaar[[#This Row],[CategorieCode]],0),0) -> 0 | I9: =IF(report_B_CategorieBoekjaar[[#This Row],[BedrijfsCode]]="001",IF(report_B_CategorieBoekjaar[[#This Row],[Boekjaar]]=Projectbegroting!$K$1,report_B_CategorieBoekjaar[[#This Row],[CategorieCode]],0),0) -> 520
A10: 001 | B10: 46023 | C10: 542 | D10: Multimedia(re)producties | E10: Kosten | F10: 0 | G10: 0 | H10: =IF(report_B_CategorieBoekjaar[[#This Row],[BedrijfsCode]]="002",IF(report_B_CategorieBoekjaar[[#This Row],[Boekjaar]]=Projectbegroting!$K$1,report_B_CategorieBoekjaar[[#This Row],[CategorieCode]],0),0) -> 0 | I10: =IF(report_B_CategorieBoekjaar[[#This Row],[BedrijfsCode]]="001",IF(report_B_CategorieBoekjaar[[#This Row],[Boekjaar]]=Projectbegroting!$K$1,report_B_CategorieBoekjaar[[#This Row],[CategorieCode]],0),0) -> 542
A11: 001 | B11: 46023 | C11: 543 | D11: ICT diensten | E11: Kosten | F11: 0 | G11: 0 | H11: =IF(report_B_CategorieBoekjaar[[#This Row],[BedrijfsCode]]="002",IF(report_B_CategorieBoekjaar[[#This Row],[Boekjaar]]=Projectbegroting!$K$1,report_B_CategorieBoekjaar[[#This Row],[CategorieCode]],0),0) -> 0 | I11: =IF(report_B_CategorieBoekjaar[[#This Row],[BedrijfsCode]]="001",IF(report_B_CategorieBoekjaar[[#This Row],[Boekjaar]]=Projectbegroting!$K$1,report_B_CategorieBoekjaar[[#This Row],[CategorieCode]],0),0) -> 543
A12: 001 | B12: 46023 | C12: 560 | D12: Examen- en itemconstructie (niet cg) | E12: Kosten | F12: 0 | G12: 0 | H12: =IF(report_B_CategorieBoekjaar[[#This Row],[BedrijfsCode]]="002",IF(report_B_CategorieBoekjaar[[#This Row],[Boekjaar]]=Projectbegroting!$K$1,report_B_CategorieBoekjaar[[#This Row],[CategorieCode]],0),0) -> 0 | I12: =IF(report_B_CategorieBoekjaar[[#This Row],[BedrijfsCode]]="001",IF(report_B_CategorieBoekjaar[[#This Row],[Boekjaar]]=Projectbegroting!$K$1,report_B_CategorieBoekjaar[[#This Row],[CategorieCode]],0),0) -> 560
A13: 001 | B13: 46023 | C13: 562 | D13: Examenbegeleiders, surveillanten | E13: Kosten | F13: 0 | G13: 0 | H13: =IF(report_B_CategorieBoekjaar[[#This Row],[BedrijfsCode]]="002",IF(report_B_CategorieBoekjaar[[#This Row],[Boekjaar]]=Projectbegroting!$K$1,report_B_CategorieBoekjaar[[#This Row],[CategorieCode]],0),0) -> 0 | I13: =IF(report_B_CategorieBoekjaar[[#This Row],[BedrijfsCode]]="001",IF(report_B_CategorieBoekjaar[[#This Row],[Boekjaar]]=Projectbegroting!$K$1,report_B_CategorieBoekjaar[[#This Row],[CategorieCode]],0),0) -> 562
... A2387: 002 | B2387: 43101 | C2387: WO-I | D2387: Wetenschappelijk onderzoeker inleen | E2387: Inhuur | F2387: 0 | G2387: 0 | H2387: =IF(report_B_CategorieBoekjaar[[#This Row],[BedrijfsCode]]="002",IF(report_B_CategorieBoekjaar[[#This Row],[Boekjaar]]=Projectbegroting!$K$1,report_B_CategorieBoekjaar[[#This Row],[CategorieCode]],0),0) -> 0 | I2387: =IF(report_B_CategorieBoekjaar[[#This Row],[BedrijfsCode]]="001",IF(report_B_CategorieBoekjaar[[#This Row],[Boekjaar]]=Projectbegroting!$K$1,report_B_CategorieBoekjaar[[#This Row],[CategorieCode]],0),0) -> 0

Sheet report B_Project
A1: BedrijfsCode | B1: ProjectCode | C1: ProjectNaam | D1: HoofdProjectCode | E1: KlantNummer | F1: KlantNaam | G1: DatumBegin | H1: DatumEinde | I1: ProjectStatus | J1: ContractId | K1: BTWCode | L1: ProjectGroep | M1: PersoneelsNummerProjectLeider | N1: NaamProjectLeider | O1: PersoneelsNummerVerkoper | P1: NaamVerkoper | Q1: PersoneelsNummerControler | R1: NaamController | S1: SorteerCode1 | T1: SorteerCode2 | U1: SorteerCode3 | V1: GrootboekAccount | W1: Kostenplaats | X1: Kostendrager | Y1: Variant | Z1: Project
A2: 002 | B2: LIBLVSALG | C2: Tijdproject Leerling in beeld volgsysteem PO | G2: 45302 | H2: 45302 | I2: In behandeling | L2: InternUur | V2: -5110-LIBLVS--LIBLVSALG | W2: 5110 | X2: LIBLVS | Z2: LIBLVSALG
A3: 002 | B3: TRAINCERTPO | C3: Tijdproject Training en Certificering PO | G3: 45302 | H3: 45302 | I3: In behandeling | L3: InternUur | V3: -5110-TRAINCERTPO--TRAINCERTPO | W3: 5110 | X3: TRAINCERTPO | Z3: TRAINCERTPO--TRAINCERTPO
A4: 002 | B4: LIBDSTALG | C4: Tijdproject Leerling in beeld doorstroomtoets | G4: 45302 | H4: 45302 | I4: In behandeling | L4: InternUur | V4: -5111-LIBDST--LIBDSTALG | W4: 5111 | X4: LIBDST | Z4: LIBDSTALG
A5: 002 | B5: CVVOCOG | C5: Tijdproject CVVO Cognitief | G5: 45302 | H5: 45302 | I5: In behandeling | L5: InternUur | V5: -5120-CVVO-COG-CVVOCOG | W5: 5120 | X5: CVVO | Y5: COG | Z5: CVVOCOG
A6: 002 | B6: CVVOALG | C6: Tijdproject CVVO Algemeen | G6: 45302 | H6: 45302 | I6: In behandeling | L6: InternUur | V6: -5120-CVVO--CVVOALG | W6: 5120 | X6: CVVO | Z6: CVVOALG
A7: 002 | B7: CVVOT0 | C7: Tijdproject CVVO Toets 0 | G7: 45302 | H7: 45302 | I7: In behandeling | L7: InternUur | V7: -5120-CVVO-T0-CVVOT0 | W7: 5120 | X7: CVVO | Y7: T0 | Z7: CVVOT0
A8: 002 | B8: CVVOT1 | C8: Tijdproject CVVO Toets 1 | G8: 45302 | H8: 45302 | I8: In behandeling | L8: InternUur | V8: -5120-CVVO-T1-CVVOT1 | W8: 5120 | X8: CVVO | Y8: T1 | Z8: CVVOT1
A9: 002 | B9: CVVOT2 | C9: Tijdproject CVVO Toets 2 | G9: 45302 | H9: 45302 | I9: In behandeling | L9: InternUur | V9: -5120-CVVO-T2-CVVOT2 | W9: 5120 | X9: CVVO | Y9: T2 | Z9: CVVOT2
A10: 002 | B10: CVVOT3 | C10: Tijdproject CVVO Toets 3 | G10: 45302 | H10: 45302 | I10: In behandeling | L10: InternUur | V10: -5120-CVVO-T3-CVVOT3 | W10: 5120 | X10: CVVO | Y10: T3 | Z10: CVVOT3
A11: 002 | B11: CVVOVSO | C11: Tijdproject CVVO VSO en PRO | G11: 45302 | H11: 45302 | I11: In behandeling | L11: InternUur | V11: -5120-CVVO-VSO-CVVOVSO | W11: 5120 | X11: CVVO | Y11: VSO | Z11: CVVOVSO
A12: 002 | B12: KLTDUI | C12: Tijdproject Kijk en luistertoets Duits | G12: 45302 | H12: 45302 | I12: In behandeling | L12: InternUur | V12: -5120-KLT-DUI-KLTDUI | W12: 5120 | X12: KLT | Y12: DUI | Z12: KLTDUI
A13: 002 | B13: KLTENG | C13: Tijdproject Kijk en luistertoets Engels | G13: 45302 | H13: 45302 | I13: In behandeling | L13: InternUur | V13: -5120-KLT-ENG-KLTENG | W13: 5120 | X13: KLT | Y13: ENG | Z13: KLTENG
A14: 002 | B14: KLTFRA | C14: Tijdproject Kijk en luistertoets Frans | G14: 45302 | H14: 45302 | I14: In behandeling | L14: InternUur | V14: -5120-KLT-FRA-KLTFRA | W14: 5120 | X14: KLT | Y14: FRA | Z14: KLTFRA
A15: 002 | B15: KLTALG | C15: Tijdproject Kijk en luistertoets algemeen | G15: 45302 | H15: 45302 | I15: In behandeling | L15: InternUur | V15: -5120-KLT--KLTALG | W15: 5120 | X15: KLT | Z15: KLTALG
A16: 002 | B16: KLTNED | C16: Tijdproject Kijk en luistertoets Nederlands | G16: 45302 | H16: 45302 | I16: In behandeling | L16: InternUur | V16: -5120-KLT-NED-KLTNED | W16: 5120 | X16: KLT | Y16: NED | Z16: KLTNED
A17: 002 | B17: KLTSPA | C17: Tijdproject Kijk en luistertoets Spaans | G17: 45302 | H17: 45302 | I17: In behandeling | L17: InternUur | V17: -5120-KLT-SPA-KLTSPA | W17: 5120 | X17: KLT | Y17: SPA | Z17: KLTSPA
A18: 002 | B18: TRAINCERTVO | C18: Tijdproject Training en Certificering VO | G18: 45302 | H18: 45302 | I18: In behandeling | L18: InternUur | V18: -5120-TRAINCERTVO--TRAINCERTVO | W18: 5120 | X18: TRAINCERTVO | Z18: TRAINCERTVO--TRAINCERTVO
A19: 002 | B19: BONDERW | C19: Tijdproject beroepsonderwijs algemeen | G19: 45302 | H19: 45302 | I19: In behandeling | L19: InternUur | V19: -5310-BONDERW--BONDERW | W19: 5310 | X19: BONDERW | Z19: BONDERW--BONDERW
A20: 002 | B20: PABOPAR | C20: Tijdproject beroepsonderwijs Pabo Particulier | G20: 45302 | H20: 45302 | I20: In behandeling | L20: InternUur | V20: -5310-BONDERW-PABOPAR-PABOPAR | W20: 5310 | X20: BONDERW | Y20: PABOPAR | Z20: PABOPAR-PABOPAR
A21: 002 | B21: TRAINCERTHO | C21: Tijdproject Training en Certificering HO | G21: 45322 | H21: 45322 | I21: In behandeling | L21: InternUur | V21: -5310-BONDERW-TRAINCERT-TRAINCERTHO | W21: 5310 | X21: BONDERW | Y21: TRAINCERT | Z21: TRAINCERTHO
A22: 002 | B22: TRAINCERTMBO | C22: Tijdproject Training en Certificering MBO | G22: 45292 | H22: 45292 | I22: In behandeling | L22: InternUur | V22: -5310-BONDERW-TRAINCERT-TRAINCERTMBO | W22: 5310 | X22: BONDERW | Y22: TRAINCERT | Z22: TRAINCERTMBO
A23: 002 | B23: TALENALG | C23: Tijdproject Talen Algemeen | G23: 45292 | H23: 45292 | I23: In behandeling | L23: InternUur | V23: -5310-TALEN--TALENALG | W23: 5310 | X23: TALEN | Z23: TALENALG
A24: 002 | B24: TRAINCERTALG | C24: Tijdproject Training en Certificering algemeen | G24: 45302 | H24: 45302 | I24: In behandeling | L24: InternUur | V24: -5310-TRAINCERTVO--TRAINCERTALG | W24: 5310 | X24: TRAINCERTVO | Z24: TRAINCERTALG
A25: 002 | B25: ZMBODEM | C25: Tijdproject Zakelijke markt Bodemenergie | G25: 45302 | H25: 45302 | I25: In behandeling | L25: InternUur | V25: -5310-ZM-BODEM-ZMBODEM | W25: 5310 | X25: ZM | Y25: BODEM | Z25: ZMBODEM
A26: 002 | B26: ZMCDD | C26: Tijdproject Zakelijke Markt CDD | G26: 45292 | H26: 45292 | I26: In behandeling | K26: NL | L26: InternUur | V26: -5310-ZM-CDD-ZMCDD | W26: 5310 | X26: ZM | Y26: CDD | Z26: ZMCDD
A27: 002 | B27: ZMISSOEPA | C27: Tijdproject Zakelijke markt ISSO Energie prestatie | G27: 45302 | H27: 45302 | I27: In behandeling | L27: InternUur | V27: -5310-ZM-ISSOEPA-ZMISSOEPA | W27: 5310 | X27: ZM | Y27: ISSOEPA | Z27: ZMISSOEPA
A28: 002 | B28: ZMMEDREK | C28: Tijdproject Zakelijke markt Medisch Rekenen | G28: 45292 | H28: 45292 | I28: In behandeling | L28: InternUur | V28: -5310-ZM-MEDREK-ZMMEDREK | W28: 5310 | X28: ZM | Y28: MEDREK | Z28: ZMMEDREK
A29: 002 | B29: ZMISSOLPA | C29: Tijdproject Zakelijke markt ISSO legionella preventie | G29: 45302 | H29: 45302 | I29: In behandeling | L29: InternUur | V29: -5310-ZM-ISSOLPA-ZMISSOLPA | W29: 5310 | X29: ZM | Y29: ISSOLPA | Z29: ZMISSOLPA
A30: 002 | B30: ZMLASSER | C30: Tijdproject Zakelijke markt Certificering PE Lassers | G30: 45302 | H30: 45302 | I30: In behandeling | L30: InternUur | V30: -5310-ZM-LASSER-ZMLASSER | W30: 5310 | X30: ZM | Y30: LASSER | Z30: ZMLASSER
A31: 002 | B31: ZMNCTV | C31: Tijdproject Zakelijke markt BAL en BAST | G31: 45302 | H31: 45302 | I31: In behandeling | L31: InternUur | V31: -5310-ZM-NCTV-ZMNCTV | W31: 5310 | X31: ZM | Y31: NCTV | Z31: ZMNCTV
A32: 002 | B32: ZMNVHP | C32: Tijdproject Zakelijke markt NVHP | G32: 45302 | H32: 45302 | I32: In behandeling | L32: InternUur | V32: -5310-ZM-NVHP-ZMNVHP | W32: 5310 | X32: ZM | Y32: NVHP | Z32: ZMNVHP
A33: 002 | B33: ZMVAKMANROUTE | C33: Tijdproject Zakelijke markt ZM Vakmanschapsroutes | G33: 45302 | H33: 45302 | I33: In behandeling | L33: InternUur | V33: -5310-ZM-VAKMANROUTE-ZMVAKMANROUTE | W33: 5310 | X33: ZM | Y33: VAKMANROUTE | Z33: ZMVAKMANROUTE
A34: 002 | B34: ZMALG | C34: Tijdproject Zakelijke markt algemeen | G34: 45302 | H34: 45302 | I34: In behandeling | L34: InternUur | V34: -5310-ZM--ZMALG | W34: 5310 | X34: ZM | Z34: ZMALG
A35: 002 | B35: 10001 | C35: 1e generatie SO / SBO BL | E35: 10021301 | F35: Cito | G35: 42737 | H35: 43465 | I35: Gereed | J35: 2000000 | K35: NL-B | L35: OVER | V35: --Uitgeverij--10001 | X35: Uitgeverij | Z35: 10001
A36: 002 | B36: 10002 | C36: 1e generatie SO / SBO RW | E36: 10021301 | F36: Cito | G36: 42737 | H36: 43465 | I36: Gereed | J36: 2000000 | K36: NL-B | L36: OVER | V36: --Uitgeverij--10002 | X36: Uitgeverij | Z36: 10002
A37: 002 | B37: 10003 | C37: 1e generatie SO / SBO SP | E37: 10021301 | F37: Cito | G37: 42737 | H37: 43465 | I37: Gereed | J37: 2000000 | K37: NL-B | L37: OVER | V37: --Uitgeverij--10003 | X37: Uitgeverij | Z37: 10003
A38: 002 | B38: 10004 | C38: 2e generatie LOVS PO BL | E38: 10021301 | F38: Cito | G38: 42737 | H38: 43465 | I38: Gereed | J38: 2000000 | K38: NL-B | L38: OVER | V38: --Uitgeverij--10004 | X38: Uitgeverij | Z38: 10004
A39: 002 | B39: 10005 | C39: 2e generatie LOVS PO RW | E39: 10021301 | F39: Cito | G39: 42737 | H39: 43465 | I39: Gereed | J39: 2000000 | K39: NL-B | L39: OVER | V39: --Uitgeverij--10005 | X39: Uitgeverij | Z39: 10005
A40: 002 | B40: 10006 | C40: 2e generatie LOVS PO SP | E40: 10021301 | F40: Cito | G40: 42737 | H40: 43465 | I40: Gereed | J40: 2000000 | K40: NL-B | L40: OVER | V40: --Uitgeverij--10006 | X40: Uitgeverij | Z40: 10006
A41: 002 | B41: 10007 | C41: Algemeen | E41: 10021301 | F41: Cito | G41: 42737 | H41: 43465 | I41: Gereed | J41: 2000000 | K41: NL-B | L41: OVER | V41: --Uitgeverij--10007 | X41: Uitgeverij | Z41: 10007
A42: 002 | B42: 10008 | C42: B&B | E42: 10021301 | F42: Cito | G42: 42737 | H42: 43465 | I42: Gereed | J42: 2000000 | K42: NL-B | L42: OVER | V42: --Uitgeverij--10008 | X42: Uitgeverij | Z42: 10008
A43: 002 | B43: 10009 | C43: Basisbewerkingen RW | E43: 10021301 | F43: Cito | G43: 42737 | H43: 43465 | I43: Gereed | J43: 2000000 | K43: NL-B | L43: OVER | V43: --Uitgeverij--10009 | X43: Uitgeverij | Z43: 10009
A44: 002 | B44: 10010 | C44: Begrijpend luisteren 3.0 | E44: 10021301 | F44: Cito | G44: 42737 | H44: 43465 | I44: Gereed | J44: 2000000 | K44: NL-B | L44: OVER | V44: --Uitgeverij--10010 | X44: Uitgeverij | Z44: 10010
A45: 002 | B45: 10011 | C45: Diversen | E45: 10021301 | F45: Cito | G45: 42737 | H45: 43465 | I45: Gereed | J45: 2000000 | K45: NL-B | L45: OVER | V45: --Uitgeverij--10011 | X45: Uitgeverij | Z45: 10011
A46: 002 | B46: 10012 | C46: DMT-AVI 2.0 | E46: 10021301 | F46: Cito | G46: 42737 | H46: 43465 | I46: Gereed | J46: 2000000 | K46: NL-B | L46: OVER | V46: --Uitgeverij--10012 | X46: Uitgeverij | Z46: 10012
... A69: 002 | B69: 10035 | C69: Woordenschat 2.0 | E69: 10021301 | F69: Cito | G69: 42737 | H69: 43465 | I69: Gereed | J69: 2000000 | K69: NL-B | L69: OVER | V69: --Uitgeverij--10035 | X69: Uitgeverij | Z69: 10035
A70: 002 | B70: ZMBOAOV | C70: Tijdproject Zakelijke markt BOA OV | G70: 45302 | H70: 45302 | I70: Gereed | L70: InternUur | V70: --ZM-BOAOV-ZMBOAOV | X70: ZM | Y70: BOAOV | Z70: ZMBOAOV
A71: 002 | B71: 30567 | C71: Kennis BES Eilanden | E71: 10027734 | F71: Ministerie van Justitie en Veiligheid | G71: 44927 | H71: 44927 | I71: Aangemaakt | J71: 2000214 | K71: NL-B | L71: OiOvD | M71: 13495 | N71: Loes van den Heuvel | S71: AUT-POC | U71: TK INBURGE | V71: -5310-TOM-OH-30567 | W71: 5310 | X71: TOM | Y71: OH | Z71: 30567
A72: 002 | B72: KIBALG | C72: Tijdproject Kleuter in beeld | G72: 45302 | H72: 45302 | I72: In behandeling | L72: InternUur | M72: 15335 | N72: Britt Thomassen | V72: -5110-KIB--KIBALG | W72: 5110 | X72: KIB | Z72: KIBALG
A73: 002 | B73: 30560 | C73: Kleuter in Beeld 2023 (vh 30384) | E73: 56824 | F73: InnovatieNul13 | G73: 45195 | H73: 45195 | I73: Gereed | J73: 2000263 | K73: NL-B | L73: OiOvD | M73: 2666 | N73: Sanne Lecluijze | V73: -5110-Uitgeverij-PO-30560 | W73: 5110 | X73: Uitgeverij | Y73: PO | Z73: 30560
A74: 002 | B74: 30460 | C74: LP18 QuestifyPlayer naar Qti | E74: 10021301 | F74: Cito | G74: 44256 | H74: 44256 | I74: Gereed | J74: 2000000 | K74: NL-B | L74: OVER | M74: 2666 | N74: Sanne Lecluijze | V74: -5310-TOM-Overig-30460 | W74: 5310 | X74: TOM | Y74: Overig | Z74: 30460
A75: 001 | B75: 20122 | C75: INVALSI | E75: 1000058 | F75: INVALSI | G75: 44866 | H75: 44866 | I75: Gereed | J75: 1000045 | K75: EU-B | L75: OKI | M75: 2668 | N75: Remco Feskens | S75: Overig | V75: -3010-OKI-Overig-20122 | W75: 3010 | X75: OKI | Y75: Overig | Z75: 20122
A76: 001 | B76: 20171 | C76: IVIT Infraprojecten 2024 | E76: 1000002 | F76: Cito Stichting (intern project) | G76: 45292 | H76: 45657 | I76: Aangemaakt | J76: 1000002 | L76: Kosten | M76: 3428 | N76: Pieta Rozema | V76: ----20171 | Z76: 20171
A77: 001 | B77: 20171-01 | C77: nog te bepalen opex | D77: 20171 | E77: 1000002 | F77: Cito Stichting (intern project) | G77: 45292 | H77: 45657 | I77: Aangemaakt | J77: 1000002 | L77: Kosten | M77: 3428 | N77: Pieta Rozema | V77: ----20171\-01 | Z77: 20171-01
A78: 001 | B78: 20171-02 | C78: IVIT Infra aanschaf laptops | D78: 20171 | E78: 1000002 | F78: Cito Stichting (intern project) | G78: 45292 | H78: 45657 | I78: Aangemaakt | J78: 1000002 | L78: Invest | M78: 3428 | N78: Pieta Rozema | V78: ----20171\-02 | Z78: 20171-02
A79: 001 | B79: 20171-03 | C79: IVIT Infra vervangen Unity | D79: 20171 | E79: 1000002 | F79: Cito Stichting (intern project) | G79: 45292 | H79: 45657 | I79: Aangemaakt | J79: 1000002 | L79: Invest | M79: 3428 | N79: Pieta Rozema | V79: ----20171\-03 | Z79: 20171-03
A80: 002 | B80: 30500 | C80: PBV08 Modernisering Lamark (naar QTI) | E80: 10021301 | F80: Cito | G80: 44562 | H80: 44926 | I80: Gereed | J80: 2000000 | K80: NL | L80: OVER | M80: 3459 | N80: Noah Ferron | S80: AUT-POC | V80: -7040-Uitgeverij-Overig-30500 | W80: 7040 | X80: Uitgeverij | Y80: Overig | Z80: 30500
A81: 001 | B81: 20238 | C81: Cyprus - Teacher recruitment Exams NTRS | E81: 1000102 | F81: Cyprus Testing Services | G81: 46023 | H81: 46023 | I81: In behandeling | J81: 1000088 | K81: EU-V | L81: CITOLABINT | M81: 35335 | N81: Josine Verhagen | S81: Overig | V81: -3010---20238 | W81: 3010 | Z81: 20238
A82: 001 | B82: 20238-01 | C82: Cyprus - Teacher recruitment Exams NTRS 2026 | D82: 20238 | E82: 1000102 | F82: Cyprus Testing Services | G82: 46023 | H82: 46077 | I82: In behandeling | J82: 1000088 | K82: EU-V | L82: CITOLABINT | M82: 35335 | N82: Josine Verhagen | S82: Overig | T82: Int | V82: -3010---20238\-01 | W82: 3010 | Z82: 20238-01
A83: 002 | B83: 30181 | C83: VO 4e Gen CVVO Vernieuwde rapportage - IVIT | E83: 10021301 | F83: Cito | G83: 43467 | H83: 43920 | I83: Gereed | J83: 2000000 | K83: NL-B | L83: OVER | M83: 2071 | N83: Zeger van Vreeswijk | O83: 1445 | P83: Henriëtte de Groot | V83: -5120-Uitgeverij-VO-30181 | W83: 5120 | X83: Uitgeverij | Y83: VO | Z83: 30181
A84: 002 | B84: 30005 | C84: Ondersteuning volgtoetsen vervolg | E84: 10021362 | F84: Expertisecentrum voor Toetsen | G84: 43299 | H84: 43404 | I84: Gereed | J84: 2000134 | K84: EX-B | L84: TrainCons | M84: 1497 | N84: Wil Knappers | O84: 1308 | P84: Frans Kleintjes | V84: -5220-TA-Int-30005 | W84: 5220 | X84: TA | Y84: Int | Z84: 30005
A85: 002 | B85: 30302 | C85: KLT IVIT | E85: 10021301 | F85: Cito | G85: 43831 | H85: 43874 | I85: Gereed | J85: 2000000 | K85: NL-B | L85: OVER | M85: 2718 | N85: Asther den Boogert | O85: 1445 | P85: Henriëtte de Groot | V85: -5130-Uitgeverij-VO-30302 | W85: 5130 | X85: Uitgeverij | Y85: VO | Z85: 30302
A86: 001 | B86: 20120 | C86: Innovation consultancy IB | E86: 1000057 | F86: IB Unites States BU | G86: 44844 | H86: 44844 | I86: Gereed | J86: 1000044 | K86: EX-B | L86: OKI | M86: 2848 | N86: Romy Noordhof | O86: 2377 | P86: Saskia Wools | S86: Overig | V86: -3030-OKI-Overig-20120 | W86: 3030 | X86: OKI | Y86: Overig | Z86: 20120
A87: 002 | B87: 30313 | C87: IT TK 2020 | E87: 10021301 | F87: Cito | G87: 43983 | H87: 43999 | I87: Gereed | J87: 2000000 | K87: NL-B | L87: OVER | M87: 16445 | N87: Kelly van der Vlies | O87: 2435 | P87: Jacqueline Visser | T87: Activ | V87: -5310-TOM-Overig-30313 | W87: 5310 | X87: TOM | Y87: Overig | Z87: 30313
A88: 002 | B88: 30315 | C88: LP08 LVS Engels | E88: 10021301 | F88: Cito | G88: 43983 | H88: 44000 | I88: Gereed | J88: 2000000 | K88: NL-B | L88: OVER | M88: 2666 | N88: Sanne Lecluijze | O88: 2435 | P88: Jacqueline Visser | T88: Activ | V88: -5110-Uitgeverij-PO-30315 | W88: 5110 | X88: Uitgeverij | Y88: PO | Z88: 30315
A89: 001 | B89: 18361 | C89: MS Dynamics 365 | E89: 1000002 | F89: Cito Stichting (intern project) | G89: 43102 | H89: 43465 | I89: Gereed | J89: 1000002 | K89: NL-P | L89: FIN PROJ | M89: 2963 | N89: Jan Dekker | O89: 2963 | P89: Jan Dekker | Q89: 1538 | R89: Gerda Wijskamp | V89: -9410-Intern-Staf-18361 | W89: 9410 | X89: Intern | Y89: Staf | Z89: 18361
A90: 001 | B90: 18329-01 | C90: Questify 2018 Stichting-SIG | D90: 18329 | E90: 1000002 | F90: Cito Stichting (intern project) | G90: 43102 | H90: 43465 | I90: Gereed | J90: 1000002 | K90: NL-P | L90: FIN PROJ | M90: 2355 | N90: René van der Burgh | O90: 2994 | P90: Peter Jan Thierry | Q90: 1538 | R90: Gerda Wijskamp | V90: -9580-Intern-Staf-18329\-01 | W90: 9580 | X90: Intern | Y90: Staf | Z90: 18329-01
A91: 001 | B91: 18329-02 | C91: Questify 2018 Stichting-regulier | D91: 18329 | E91: 1000002 | F91: Cito Stichting (intern project) | G91: 43102 | H91: 43465 | I91: Gereed | J91: 1000002 | K91: NL-P | L91: FIN PROJ | M91: 2355 | N91: René van der Burgh | O91: 2994 | P91: Peter Jan Thierry | Q91: 1538 | R91: Gerda Wijskamp | V91: -9580-Intern-Staf-18329\-02 | W91: 9580 | X91: Intern | Y91: Staf | Z91: 18329-02
A92: 001 | B92: 18329-03 | C92: Questify 2018 Stichting-ontvlechting | D92: 18329 | E92: 1000002 | F92: Cito Stichting (intern project) | G92: 43102 | H92: 43465 | I92: Gereed | J92: 1000002 | K92: NL-P | L92: FIN PROJ | M92: 2355 | N92: René van der Burgh | O92: 2994 | P92: Peter Jan Thierry | Q92: 1538 | R92: Gerda Wijskamp | V92: -9580-Intern-Staf-18329\-03 | W92: 9580 | X92: Intern | Y92: Staf | Z92: 18329-03
A93: 001 | B93: 18329-04 | C93: Questify 2018 Stichting-open source | D93: 18329 | E93: 1000002 | F93: Cito Stichting (intern project) | G93: 43102 | H93: 43465 | I93: Gereed | J93: 1000002 | K93: NL-P | L93: FIN PROJ | M93: 2355 | N93: René van der Burgh | O93: 2994 | P93: Peter Jan Thierry | Q93: 1538 | R93: Gerda Wijskamp | V93: -9580-Intern-Staf-18329\-04 | W93: 9580 | X93: Intern | Y93: Staf | Z93: 18329-04
A94: 001 | B94: 18372 | C94: Uren externe medewerkers ST (headfirst) | E94: 1000002 | F94: Cito Stichting (intern project) | G94: 43102 | H94: 43465 | I94: Gereed | J94: 1000002 | K94: NL-P | L94: FIN PROJ | M94: 2899 | N94: Jan Pieter de Boer | O94: 2994 | P94: Peter Jan Thierry | Q94: 1538 | R94: Gerda Wijskamp | V94: -9570-Intern-Staf-18372 | W94: 9570 | X94: Intern | Y94: Staf | Z94: 18372
A95: 001 | B95: 18508 | C95: Stichting Cito Algemeen | E95: 1000002 | F95: Cito Stichting (intern project) | G95: 43102 | H95: 43465 | I95: Gereed | J95: 1000002 | K95: NL-P | L95: FIN PROJ | M95: 2298 | N95: Nancy Hakstege - Willemsen | O95: 3059 | P95: Anneke Blok | Q95: 1538 | R95: Gerda Wijskamp | V95: -9100-Intern-Staf-18508 | W95: 9100 | X95: Intern | Y95: Staf | Z95: 18508
A96: 001 | B96: 18508-01 | C96: Strategische communicatie | D96: 18508 | E96: 1000002 | F96: Cito Stichting (intern project) | G96: 43102 | H96: 43465 | I96: Gereed | J96: 1000002 | K96: NL-P | L96: FIN PROJ | M96: 2298 | N96: Nancy Hakstege - Willemsen | O96: 3059 | P96: Anneke Blok | Q96: 1538 | R96: Gerda Wijskamp | V96: -9100-Intern-Staf-18508\-01 | W96: 9100 | X96: Intern | Y96: Staf | Z96: 18508-01
A97: 001 | B97: 18508-02 | C97: HRM | D97: 18508 | E97: 1000002 | F97: Cito Stichting (intern project) | G97: 43102 | H97: 43465 | I97: Gereed | J97: 1000002 | K97: NL-P | L97: FIN PROJ | M97: 2298 | N97: Nancy Hakstege - Willemsen | O97: 3059 | P97: Anneke Blok | Q97: 1538 | R97: Gerda Wijskamp | V97: -9100-Intern-Staf-18508\-02 | W97: 9100 | X97: Intern | Y97: Staf | Z97: 18508-02
A98: 001 | B98: 18508-03 | C98: Diversen | D98: 18508 | E98: 1000002 | F98: Cito Stichting (intern project) | G98: 43102 | H98: 43465 | I98: Gereed | J98: 1000002 | K98: NL-P | L98: FIN PROJ | M98: 2298 | N98: Nancy Hakstege - Willemsen | O98: 3059 | P98: Anneke Blok | Q98: 1538 | R98: Gerda Wijskamp | V98: -9100-Intern-Staf-18508\-03 | W98: 9100 | X98: Intern | Y98: Staf | Z98: 18508-03
A99: 001 | B99: 20025 | C99: Stichting Cito Algemeen | E99: 1000002 | F99: Cito Stichting (intern project) | G99: 43467 | H99: 43467 | I99: Gereed | J99: 1000002 | K99: NL-P | L99: FIN PROJ | M99: 2298 | N99: Nancy Hakstege - Willemsen | O99: 3059 | P99: Anneke Blok | Q99: 1538 | R99: Gerda Wijskamp | V99: -9100-Intern-Staf-20025 | W99: 9100 | X99: Intern | Y99: Staf | Z99: 20025
A100: 001 | B100: 20025-01 | C100: Marketing ondersteuning | D100: 20025 | E100: 1000002 | F100: Cito Stichting (intern project) | G100: 43467 | H100: 43467 | I100: Gereed | J100: 1000002 | K100: NL-P | L100: FIN PROJ | M100: 2298 | N100: Nancy Hakstege - Willemsen | O100: 3059 | P100: Anneke Blok | Q100: 1538 | R100: Gerda Wijskamp | V100: -9100-Intern-Staf-20025\-01 | W100: 9100 | X100: Intern | Y100: Staf | Z100: 20025-01
A101: 001 | B101: 20025-02 | C101: HRM | D101: 20025 | E101: 1000002 | F101: Cito Stichting (intern project) | G101: 43467 | H101: 43467 | I101: Gereed | J101: 1000002 | K101: NL-P | L101: FIN PROJ | M101: 2298 | N101: Nancy Hakstege - Willemsen | O101: 3059 | P101: Anneke Blok | Q101: 1538 | R101: Gerda Wijskamp | V101: -9100-Intern-Staf-20025\-02 | W101: 9100 | X101: Intern | Y101: Staf | Z101: 20025-02
A102: 001 | B102: 20044 | C102: Stichting Cito Algemeen | E102: 1000002 | F102: Cito Stichting (intern project) | G102: 43831 | H102: 43831 | I102: Gereed | J102: 1000002 | K102: NL-V | L102: FIN PROJ | M102: 2298 | N102: Nancy Hakstege - Willemsen | O102: 3059 | P102: Anneke Blok | Q102: 1538 | R102: Gerda Wijskamp | V102: -9100-Intern-Staf-20044 | W102: 9100 | X102: Intern | Y102: Staf | Z102: 20044
A103: 001 | B103: 20044-01 | C103: Strategische communicatie | D103: 20044 | E103: 1000002 | F103: Cito Stichting (intern project) | G103: 43831 | H103: 44005 | I103: Gereed | J103: 1000002 | K103: NL-V | L103: FIN PROJ | M103: 2298 | N103: Nancy Hakstege - Willemsen | O103: 3059 | P103: Anneke Blok | Q103: 1538 | R103: Gerda Wijskamp | V103: -9100-Intern-Staf-20044\-01 | W103: 9100 | X103: Intern | Y103: Staf | Z103: 20044-01
A104: 001 | B104: 18486 | C104: Jubileum Cito 50 jaar | E104: 1000002 | F104: Cito Stichting (intern project) | G104: 43102 | H104: 43465 | I104: Gereed | J104: 1000002 | K104: NL-P | L104: FIN PROJ | M104: 3104 | N104: Corine Theuns | O104: 3059 | P104: Anneke Blok | Q104: 1538 | R104: Gerda Wijskamp | V104: -9100-Intern-Staf-18486 | W104: 9100 | X104: Intern | Y104: Staf | Z104: 18486
A105: 001 | B105: 20022 | C105: Jubileum Cito 50 jaar | E105: 1000002 | F105: Cito Stichting (intern project) | G105: 43466 | H105: 43466 | I105: Gereed | J105: 1000002 | K105: NL-P | L105: FIN PROJ | M105: 3104 | N105: Corine Theuns | O105: 3059 | P105: Anneke Blok | Q105: 1538 | R105: Gerda Wijskamp | V105: -9100-Intern-Staf-20022 | W105: 9100 | X105: Intern | Y105: Staf | Z105: 20022
A106: 002 | B106: 30325 | C106: Correctie voor overlopende kosten 2019 | E106: 10021301 | F106: Cito | G106: 43467 | H106: 43467 | I106: Gereed | J106: 2000000 | K106: NL-B | L106: OVER | M106: 2084 | N106: Janny Harmsen - van Rijkom | O106: 3369 | P106: Daniëlle Roelofsma | Q106: 17055 | R106: Maarten van de Veen | V106: -7020-Overige-Overig-30325 | W106: 7020 | X106: Overige | Y106: Overig | Z106: 30325
A107: 002 | B107: 30378 | C107: Marketing Intelligence en automation | E107: 2000002 | F107: Cito BV (intern project) | G107: 44197 | H107: 44197 | I107: Aangemaakt | J107: 2000129 | K107: NL-B | L107: FIN PROJ | M107: 4205 | N107: Serge Hoek | O107: 4205 | P107: Serge Hoek | Q107: 17055 | R107: Maarten van de Veen | V107: -5610-Overige-Overig-30378 | W107: 5610 | X107: Overige | Y107: Overig | Z107: 30378
A108: 002 | B108: 30378-0001 | C108: Marketing Intelligence en automation 2021 | D108: 30378 | E108: 2000002 | F108: Cito BV (intern project) | G108: 44197 | H108: 44197 | I108: Gereed | J108: 2000129 | K108: NL-B | L108: FIN PROJ | M108: 4205 | N108: Serge Hoek | O108: 4205 | P108: Serge Hoek | Q108: 17055 | R108: Maarten van de Veen | V108: -5610-Overige-Overig-30378\-0001 | W108: 5610 | X108: Overige | Y108: Overig | Z108: 30378-0001
A109: 002 | B109: 30380 | C109: Marketing & Communicatie | E109: 2000002 | F109: Cito BV (intern project) | G109: 44197 | H109: 44197 | I109: Gereed | J109: 2000129 | K109: NL-P | L109: FIN PROJ | M109: 4205 | N109: Serge Hoek | O109: 4205 | P109: Serge Hoek | Q109: 17055 | R109: Maarten van de Veen | V109: -5610-Overige-Overig-30380 | W109: 5610 | X109: Overige | Y109: Overig | Z109: 30380
A110: 002 | B110: 30380-0001 | C110: Marketing & Communicatie 2021 | D110: 30380 | E110: 2000002 | F110: Cito BV (intern project) | G110: 44197 | H110: 44197 | I110: Gereed | J110: 2000129 | K110: NL-P | L110: FIN PROJ | M110: 4205 | N110: Serge Hoek | O110: 4205 | P110: Serge Hoek | Q110: 17055 | R110: Maarten van de Veen | V110: -5610-Overige-Overig-30380\-0001 | W110: 5610 | X110: Overige | Y110: Overig | Z110: 30380-0001
A111: 002 | B111: 30379 | C111: Klantbeheer en CRM | E111: 2000002 | F111: Cito BV (intern project) | G111: 44197 | H111: 44197 | I111: Gereed | J111: 2000129 | K111: NL-B | L111: FIN PROJ | M111: 4205 | N111: Serge Hoek | O111: 4205 | P111: Serge Hoek | Q111: 17055 | R111: Maarten van de Veen | V111: -5610-Overige-Overig-30379 | W111: 5610 | X111: Overige | Y111: Overig | Z111: 30379
A112: 002 | B112: 30379-0001 | C112: Klantbeheer en CRM 2021 | D112: 30379 | E112: 2000002 | F112: Cito BV (intern project) | G112: 44197 | H112: 44197 | I112: Gereed | J112: 2000129 | K112: NL-B | L112: FIN PROJ | M112: 4205 | N112: Serge Hoek | O112: 4205 | P112: Serge Hoek | Q112: 17055 | R112: Maarten van de Veen | V112: -5610-Overige-Overig-30379\-0001 | W112: 5610 | X112: Overige | Y112: Overig | Z112: 30379-0001
A113: 002 | B113: 30377-0001 | C113: Webshop 2021 | D113: 30377 | E113: 2000002 | F113: Cito BV (intern project) | G113: 44197 | H113: 44197 | I113: Gereed | J113: 2000129 | K113: NL-B | L113: FIN PROJ | M113: 4205 | N113: Serge Hoek | O113: 4205 | P113: Serge Hoek | Q113: 17055 | R113: Maarten van de Veen | T113: Activ | V113: -5610-Overige-Overig-30377\-0001 | W113: 5610 | X113: Overige | Y113: Overig | Z113: 30377-0001
A114: 002 | B114: 30368 | C114: T&A Marketing | E114: 10021301 | F114: Cito | G114: 44197 | H114: 44197 | I114: Aangemaakt | J114: 2000000 | K114: NL-B | L114: DNDT | M114: 3088 | N114: Hedy Becks | O114: 4205 | P114: Serge Hoek | Q114: 17055 | R114: Maarten van de Veen | V114: -5210-TA-Overig-30368 | W114: 5210 | X114: TA | Y114: Overig | Z114: 30368
A115: 002 | B115: 30368-0001 | C115: T&A Marketing 2021 | D115: 30368 | E115: 10021301 | F115: Cito | G115: 44197 | H115: 44197 | I115: Gereed | J115: 2000000 | K115: NL-B | L115: DNDT | M115: 3088 | N115: Hedy Becks | O115: 4205 | P115: Serge Hoek | Q115: 17055 | R115: Maarten van de Veen | V115: -5210-TA-Overig-30368\-0001 | W115: 5210 | X115: TA | Y115: Overig | Z115: 30368-0001
A116: 002 | B116: 30374 | C116: Marketing Toetsketens | E116: 10021301 | F116: Cito | G116: 44197 | H116: 44197 | I116: Aangemaakt | J116: 2000000 | K116: NL-B | L116: DNDT | M116: 3088 | N116: Hedy Becks | O116: 4205 | P116: Serge Hoek | Q116: 17055 | R116: Maarten van de Veen | V116: -5320-TOM-Overig-30374 | W116: 5320 | X116: TOM | Y116: Overig | Z116: 30374
A117: 002 | B117: 30374-0001 | C117: Marketing Toetsketens 2021 | D117: 30374 | E117: 10021301 | F117: Cito | G117: 44197 | H117: 44206 | I117: Gereed | J117: 2000000 | K117: NL-B | L117: DNDT | M117: 3088 | N117: Hedy Becks | O117: 4205 | P117: Serge Hoek | Q117: 17055 | R117: Maarten van de Veen | V117: -5320-TOM-Overig-30374\-0001 | W117: 5320 | X117: TOM | Y117: Overig | Z117: 30374-0001
A118: 002 | B118: 30381 | C118: CBR afnamesysteem iTEC | E118: 10024788 | F118: CBR Afd. Crediteurenadministratie | G118: 44197 | H118: 44197 | I118: Aangemaakt | J118: 2000176 | K118: NL-B | L118: OiOvD | M118: 2131 | N118: Hanneke Bouwmans - de Jong | O118: 2950 | P118: Jasper Kwakkelstein | Q118: 17055 | R118: Maarten van de Veen | V118: -5320-TOM-TTV-30381 | W118: 5320 | X118: TOM | Y118: TTV | Z118: 30381
A119: 002 | B119: 30381-0001 | C119: CBR afnamesysteem iTEC 2021 | D119: 30381 | E119: 10024788 | F119: CBR Afd. Crediteurenadministratie | G119: 44197 | H119: 44215 | I119: Gereed | J119: 2000176 | K119: NL-B | L119: OiOvD | M119: 2131 | N119: Hanneke Bouwmans - de Jong | O119: 2950 | P119: Jasper Kwakkelstein | Q119: 17055 | R119: Maarten van de Veen | V119: -5320-TOM-TTV-30381\-0001 | W119: 5320 | X119: TOM | Y119: TTV | Z119: 30381-0001
A120: 002 | B120: 30316 | C120: Volgtoetsen taal in Caribisch Nederland | E120: 10021487 | F120: Ministerie van OCW | G120: 43831 | H120: 43853 | I120: Gereed | J120: 2000014 | K120: NL-B | L120: OiOvD | M120: 2131 | N120: Hanneke Bouwmans - de Jong | O120: 2950 | P120: Jasper Kwakkelstein | Q120: 17055 | R120: Maarten van de Veen | V120: -5310-TOM-Overig-30316 | W120: 5310 | X120: TOM | Y120: Overig | Z120: 30316
A121: 002 | B121: 30404 | C121: Verwerking antwoordbladen | E121: 10021301 | F121: Cito | G121: 44197 | H121: 44197 | I121: Aangemaakt | J121: 2000000 | K121: NL-B | L121: ExCert | M121: 2131 | N121: Hanneke Bouwmans - de Jong | O121: 2950 | P121: Jasper Kwakkelstein | Q121: 17055 | R121: Maarten van de Veen | V121: -5320-TOM-Overig-30404 | W121: 5320 | X121: TOM | Y121: Overig | Z121: 30404
A122: 002 | B122: 30404-0001 | C122: Verwerking antwoordbladen 2021 | D122: 30404 | E122: 10021301 | F122: Cito | G122: 44197 | H122: 44212 | I122: Gereed | J122: 2000000 | K122: NL-B | L122: ExCert | M122: 2131 | N122: Hanneke Bouwmans - de Jong | O122: 2950 | P122: Jasper Kwakkelstein | Q122: 17055 | R122: Maarten van de Veen | V122: -5320-TOM-Overig-30404\-0001 | W122: 5320 | X122: TOM | Y122: Overig | Z122: 30404-0001
...
